{"741":[{"id":"SV4M-025","name":"춤추새","dexNumber":741,"setId":"SV4M","setName":"미래의 일섬","localId":"025","rarity":"Common","imageBase":"","language":"ko"}],"750":[{"id":"SV5K-078","name":"만마드","dexNumber":750,"setId":"SV5K","setName":"와일드포스","localId":"078","rarity":"Unknown","imageBase":"","language":"ko"}],"761":[{"id":"SV4K-006","name":"달콤아","dexNumber":761,"setId":"SV4K","setName":"고대의 포효","localId":"006","rarity":"Common","imageBase":"","language":"ko"}],"762":[{"id":"SV4K-007","name":"달무리나","dexNumber":762,"setId":"SV4K","setName":"고대의 포효","localId":"007","rarity":"Uncommon","imageBase":"","language":"ko"}],"767":[{"id":"SV4K-021","name":"꼬시레","dexNumber":767,"setId":"SV4K","setName":"고대의 포효","localId":"021","rarity":"Common","imageBase":"","language":"ko"},{"id":"SV4K-069","name":"꼬시레","dexNumber":767,"setId":"SV4K","setName":"고대의 포효","localId":"069","rarity":"Unknown","imageBase":"","language":"ko"}]}