{"656":[{"id":"SV5a-023","name":"เคโรมัตซึ","dexNumber":656,"setId":"SV5a","setName":"หมอกสีชาด","localId":"023","rarity":"Common","imageBase":"","language":"th"}],"657":[{"id":"SV5a-024","name":"เกโคกาชิระ","dexNumber":657,"setId":"SV5a","setName":"หมอกสีชาด","localId":"024","rarity":"Common","imageBase":"","language":"th"}],"658":[{"id":"S12a-033","name":"เรเดียนต์เก็คโคกะ","dexNumber":658,"setId":"S12a","setName":"จักรวาลแห่งVSTAR","localId":"033","rarity":"Unknown","imageBase":"","language":"th"}],"659":[{"id":"SV3-095","name":"โฮรุบี","dexNumber":659,"setId":"SV3","setName":"ราชาแห่งเพลิงกาฬ","localId":"095","rarity":"Common","imageBase":"","language":"th"}],"660":[{"id":"SV3-060","name":"โฮรูโด","dexNumber":660,"setId":"SV3","setName":"ราชาแห่งเพลิงกาฬ","localId":"060","rarity":"Common","imageBase":"","language":"th"}],"661":[{"id":"SV2D-061","name":"ยายาโคมะ","dexNumber":661,"setId":"SV2D","setName":"เคลย์เบิสต์","localId":"061","rarity":"Common","imageBase":"","language":"th"}],"662":[{"id":"SV2D-012","name":"ฮิโนยาโคมะ","dexNumber":662,"setId":"SV2D","setName":"เคลย์เบิสต์","localId":"012","rarity":"Common","imageBase":"https://assets.tcgdex.net/th/SV/SV2D/012","language":"th","hostedThumbUrl":"https://raw.githubusercontent.com/froyonator/pcc-assets-a/main/th/SV2D/SV2D-012/thumb.webp","hostedFullUrl":"https://raw.githubusercontent.com/froyonator/pcc-assets-a/main/th/SV2D/SV2D-012/original.webp"}],"663":[{"id":"SV2D-013","name":"ไฟร์แอโรว์","dexNumber":663,"setId":"SV2D","setName":"เคลย์เบิสต์","localId":"013","rarity":"Uncommon","imageBase":"https://assets.tcgdex.net/th/SV/SV2D/013","language":"th","hostedThumbUrl":"https://raw.githubusercontent.com/froyonator/pcc-assets-a/main/th/SV2D/SV2D-013/thumb.webp","hostedFullUrl":"https://raw.githubusercontent.com/froyonator/pcc-assets-a/main/th/SV2D/SV2D-013/original.webp"}],"664":[{"id":"SV1V-003","name":"โคฟูคิมูชิ","dexNumber":664,"setId":"SV1V","setName":"ไวโอเล็ต ex","localId":"003","rarity":"Common","imageBase":"https://assets.tcgdex.net/th/SV/SV1V/003","language":"th","hostedThumbUrl":"https://raw.githubusercontent.com/froyonator/pcc-assets-a/main/th/SV1V/SV1V-003/thumb.webp","hostedFullUrl":"https://raw.githubusercontent.com/froyonator/pcc-assets-a/main/th/SV1V/SV1V-003/original.webp"}],"665":[{"id":"SV1V-004","name":"โคฟูไร","dexNumber":665,"setId":"SV1V","setName":"ไวโอเล็ต ex","localId":"004","rarity":"Common","imageBase":"https://assets.tcgdex.net/th/SV/SV1V/004","language":"th","hostedThumbUrl":"https://raw.githubusercontent.com/froyonator/pcc-assets-a/main/th/SV1V/SV1V-004/thumb.webp","hostedFullUrl":"https://raw.githubusercontent.com/froyonator/pcc-assets-a/main/th/SV1V/SV1V-004/original.webp"}],"666":[{"id":"SV1V-005","name":"วิวิญอง","dexNumber":666,"setId":"SV1V","setName":"ไวโอเล็ต ex","localId":"005","rarity":"Uncommon","imageBase":"https://assets.tcgdex.net/th/SV/SV1V/005","language":"th","hostedThumbUrl":"https://raw.githubusercontent.com/froyonator/pcc-assets-a/main/th/SV1V/SV1V-005/thumb.webp","hostedFullUrl":"https://raw.githubusercontent.com/froyonator/pcc-assets-a/main/th/SV1V/SV1V-005/original.webp"}],"667":[{"id":"SV1a-014","name":"ชิชิโกะ","dexNumber":667,"setId":"SV1a","setName":"ทริปเปิลบีต","localId":"014","rarity":"Common","imageBase":"https://assets.tcgdex.net/th/SV/SV1a/014","language":"th","hostedThumbUrl":"https://raw.githubusercontent.com/froyonator/pcc-assets-a/main/th/SV1a/SV1a-014/thumb.webp","hostedFullUrl":"https://raw.githubusercontent.com/froyonator/pcc-assets-a/main/th/SV1a/SV1a-014/original.webp"}],"668":[{"id":"SV1a-015","name":"คาเอ็นจิชิ","dexNumber":668,"setId":"SV1a","setName":"ทริปเปิลบีต","localId":"015","rarity":"Uncommon","imageBase":"https://assets.tcgdex.net/th/SV/SV1a/015","language":"th","hostedThumbUrl":"https://raw.githubusercontent.com/froyonator/pcc-assets-a/main/th/SV1a/SV1a-015/thumb.webp","hostedFullUrl":"https://raw.githubusercontent.com/froyonator/pcc-assets-a/main/th/SV1a/SV1a-015/original.webp"}],"669":[{"id":"SV1V-042","name":"ฟลาเบเบ","dexNumber":669,"setId":"SV1V","setName":"ไวโอเล็ต ex","localId":"042","rarity":"Common","imageBase":"","language":"th"},{"id":"SV5a-036","name":"ฟลาเบเบ","dexNumber":669,"setId":"SV5a","setName":"หมอกสีชาด","localId":"036","rarity":"Common","imageBase":"","language":"th"}],"670":[{"id":"SV1V-043","name":"ฟลาเอตเต","dexNumber":670,"setId":"SV1V","setName":"ไวโอเล็ต ex","localId":"043","rarity":"Common","imageBase":"","language":"th"},{"id":"SV5a-037","name":"ฟลาเอตเต","dexNumber":670,"setId":"SV5a","setName":"หมอกสีชาด","localId":"037","rarity":"Common","imageBase":"","language":"th"}],"671":[{"id":"SV1V-044","name":"ฟลาเจส","dexNumber":671,"setId":"SV1V","setName":"ไวโอเล็ต ex","localId":"044","rarity":"Uncommon","imageBase":"","language":"th"},{"id":"SV5a-038","name":"ฟลาเจส","dexNumber":671,"setId":"SV5a","setName":"หมอกสีชาด","localId":"038","rarity":"Uncommon","imageBase":"","language":"th"}],"672":[{"id":"SV1S-003","name":"เมเคิล","dexNumber":672,"setId":"SV1S","setName":"สการ์เล็ต ex","localId":"003","rarity":"Common","imageBase":"https://assets.tcgdex.net/th/SV/SV1S/003","language":"th","hostedThumbUrl":"https://raw.githubusercontent.com/froyonator/pcc-assets-a/main/th/SV1S/SV1S-003/thumb.webp","hostedFullUrl":"https://raw.githubusercontent.com/froyonator/pcc-assets-a/main/th/SV1S/SV1S-003/original.webp"}],"673":[{"id":"SV1S-004","name":"โกโกท","dexNumber":673,"setId":"SV1S","setName":"สการ์เล็ต ex","localId":"004","rarity":"Common","imageBase":"https://assets.tcgdex.net/th/SV/SV1S/004","language":"th","hostedThumbUrl":"https://raw.githubusercontent.com/froyonator/pcc-assets-a/main/th/SV1S/SV1S-004/thumb.webp","hostedFullUrl":"https://raw.githubusercontent.com/froyonator/pcc-assets-a/main/th/SV1S/SV1S-004/original.webp"}],"674":[{"id":"S12-052","name":"ยันชัม","dexNumber":674,"setId":"S12","setName":"ปฐมบทแห่งยุคใหม่","localId":"052","rarity":"Common","imageBase":"","language":"th"}],"675":[{"id":"S12-059","name":"โกรอนดะ","dexNumber":675,"setId":"S12","setName":"ปฐมบทแห่งยุคใหม่","localId":"059","rarity":"Uncommon","imageBase":"","language":"th"}],"679":[{"id":"SV3a-045","name":"ฮิโตทซึกิ","dexNumber":679,"setId":"SV3a","setName":"คลื่นพิโรธ","localId":"045","rarity":"Common","imageBase":"","language":"th"},{"id":"SV4M-043","name":"ฮิโตทซึกิ","dexNumber":679,"setId":"SV4M","setName":"ประกายแสงจากอนาคต","localId":"043","rarity":"Common","imageBase":"","language":"th"},{"id":"SV8a-109","name":"ฮิโตทซึกิ","dexNumber":679,"setId":"SV8a","setName":"เทศกาลเทรัสตัลex","localId":"109","rarity":"None","imageBase":"https://assets.tcgdex.net/th/SV/SV8a/109","language":"th","hostedThumbUrl":"https://raw.githubusercontent.com/froyonator/pcc-assets-a/main/th/SV8a/SV8a-109/thumb.webp","hostedFullUrl":"https://raw.githubusercontent.com/froyonator/pcc-assets-a/main/th/SV8a/SV8a-109/original.webp"}],"680":[{"id":"SV3a-046","name":"นิดังกิล","dexNumber":680,"setId":"SV3a","setName":"คลื่นพิโรธ","localId":"046","rarity":"Common","imageBase":"","language":"th"},{"id":"SV4M-044","name":"นิดังกิล","dexNumber":680,"setId":"SV4M","setName":"ประกายแสงจากอนาคต","localId":"044","rarity":"Common","imageBase":"","language":"th"},{"id":"SV8a-110","name":"นิดังกิล","dexNumber":680,"setId":"SV8a","setName":"เทศกาลเทรัสตัลex","localId":"110","rarity":"None","imageBase":"https://assets.tcgdex.net/th/SV/SV8a/110","language":"th","hostedThumbUrl":"https://raw.githubusercontent.com/froyonator/pcc-assets-a/main/th/SV8a/SV8a-110/thumb.webp","hostedFullUrl":"https://raw.githubusercontent.com/froyonator/pcc-assets-a/main/th/SV8a/SV8a-110/original.webp"}],"681":[{"id":"SV3a-047","name":"กิลการ์ด","dexNumber":681,"setId":"SV3a","setName":"คลื่นพิโรธ","localId":"047","rarity":"Rare","imageBase":"","language":"th"},{"id":"SV3a-073","name":"กิลการ์ด","dexNumber":681,"setId":"SV3a","setName":"คลื่นพิโรธ","localId":"073","rarity":"Unknown","imageBase":"","language":"th"},{"id":"SV8a-111","name":"กิลการ์ด","dexNumber":681,"setId":"SV8a","setName":"เทศกาลเทรัสตัลex","localId":"111","rarity":"None","imageBase":"https://assets.tcgdex.net/th/SV/SV8a/111","language":"th","hostedThumbUrl":"https://raw.githubusercontent.com/froyonator/pcc-assets-a/main/th/SV8a/SV8a-111/thumb.webp","hostedFullUrl":"https://raw.githubusercontent.com/froyonator/pcc-assets-a/main/th/SV8a/SV8a-111/original.webp"}],"684":[{"id":"SV6-051","name":"เพร็อพพัฟ","dexNumber":684,"setId":"SV6","setName":"หน้ากากจอมลวงตา","localId":"051","rarity":"Common","imageBase":"","language":"th"},{"id":"SV8a-067","name":"เพร็อพพัฟ","dexNumber":684,"setId":"SV8a","setName":"เทศกาลเทรัสตัลex","localId":"067","rarity":"None","imageBase":"https://assets.tcgdex.net/th/SV/SV8a/067","language":"th","hostedThumbUrl":"https://raw.githubusercontent.com/froyonator/pcc-assets-a/main/th/SV8a/SV8a-067/thumb.webp","hostedFullUrl":"https://raw.githubusercontent.com/froyonator/pcc-assets-a/main/th/SV8a/SV8a-067/original.webp"}],"685":[{"id":"SV6-052","name":"เพโรรีม","dexNumber":685,"setId":"SV6","setName":"หน้ากากจอมลวงตา","localId":"052","rarity":"Uncommon","imageBase":"","language":"th"}],"686":[{"id":"SV3-075","name":"มาอีกะ","dexNumber":686,"setId":"SV3","setName":"ราชาแห่งเพลิงกาฬ","localId":"075","rarity":"Common","imageBase":"","language":"th"}],"687":[{"id":"SV3-076","name":"คาลามาเนโร","dexNumber":687,"setId":"SV3","setName":"ราชาแห่งเพลิงกาฬ","localId":"076","rarity":"Uncommon","imageBase":"","language":"th"}],"690":[{"id":"S12-060","name":"คูซูโม","dexNumber":690,"setId":"S12","setName":"ปฐมบทแห่งยุคใหม่","localId":"060","rarity":"Common","imageBase":"","language":"th"}],"691":[{"id":"S12-061","name":"ดรามิโดโร","dexNumber":691,"setId":"S12","setName":"ปฐมบทแห่งยุคใหม่","localId":"061","rarity":"Uncommon","imageBase":"","language":"th"}],"692":[{"id":"SV1V-021","name":"อุเด็ปโป","dexNumber":692,"setId":"SV1V","setName":"ไวโอเล็ต ex","localId":"021","rarity":"Common","imageBase":"","language":"th"}],"693":[{"id":"SV1V-022","name":"บลอสเตอร์","dexNumber":693,"setId":"SV1V","setName":"ไวโอเล็ต ex","localId":"022","rarity":"Common","imageBase":"","language":"th"}],"694":[{"id":"S12-030","name":"เอลิคิเทล","dexNumber":694,"setId":"S12","setName":"ปฐมบทแห่งยุคใหม่","localId":"030","rarity":"Common","imageBase":"","language":"th"},{"id":"SV5a-028","name":"เอลิคิเทล","dexNumber":694,"setId":"SV5a","setName":"หมอกสีชาด","localId":"028","rarity":"Common","imageBase":"","language":"th"}],"695":[{"id":"S12-031","name":"เอเลซาร์ด","dexNumber":695,"setId":"S12","setName":"ปฐมบทแห่งยุคใหม่","localId":"031","rarity":"Common","imageBase":"","language":"th"},{"id":"SV5a-029","name":"เอเลซาร์ด","dexNumber":695,"setId":"SV5a","setName":"หมอกสีชาด","localId":"029","rarity":"Common","imageBase":"","language":"th"}],"700":[{"id":"SV8a-068","name":"นิมเฟีย","dexNumber":700,"setId":"SV8a","setName":"เทศกาลเทรัสตัลex","localId":"068","rarity":"None","imageBase":"https://assets.tcgdex.net/th/SV/SV8a/068","language":"th","hostedThumbUrl":"https://raw.githubusercontent.com/froyonator/pcc-assets-a/main/th/SV8a/SV8a-068/thumb.webp","hostedFullUrl":"https://raw.githubusercontent.com/froyonator/pcc-assets-a/main/th/SV8a/SV8a-068/original.webp"}],"701":[{"id":"S12a-078","name":"เรเดียนต์ลูจาบูล","dexNumber":701,"setId":"S12a","setName":"จักรวาลแห่งVSTAR","localId":"078","rarity":"Unknown","imageBase":"","language":"th"},{"id":"SV1S-045","name":"ลูจาบูล","dexNumber":701,"setId":"SV1S","setName":"สการ์เล็ต ex","localId":"045","rarity":"Rare","imageBase":"","language":"th"},{"id":"SV4a-106","name":"ลูจาบูล","dexNumber":701,"setId":"SV4a","setName":"ไชนีเทรเชอร์ex","localId":"106","rarity":"Unknown","imageBase":"","language":"th"},{"id":"SV5a-046","name":"ลูจาบูล","dexNumber":701,"setId":"SV5a","setName":"หมอกสีชาด","localId":"046","rarity":"Common","imageBase":"","language":"th"},{"id":"SV8a-084","name":"ลูจาบูล","dexNumber":701,"setId":"SV8a","setName":"เทศกาลเทรัสตัลex","localId":"084","rarity":"None","imageBase":"https://assets.tcgdex.net/th/SV/SV8a/084","language":"th","hostedThumbUrl":"https://raw.githubusercontent.com/froyonator/pcc-assets-a/main/th/SV8a/SV8a-084/thumb.webp","hostedFullUrl":"https://raw.githubusercontent.com/froyonator/pcc-assets-a/main/th/SV8a/SV8a-084/original.webp"}],"702":[{"id":"S12-045","name":"เดเด็นเนะ","dexNumber":702,"setId":"S12","setName":"ปฐมบทแห่งยุคใหม่","localId":"045","rarity":"Common","imageBase":"","language":"th"},{"id":"SV1S-031","name":"เดเด็นเนะ","dexNumber":702,"setId":"SV1S","setName":"สการ์เล็ต ex","localId":"031","rarity":"Common","imageBase":"","language":"th"}],"704":[{"id":"S12a-112","name":"นูเมรา","dexNumber":704,"setId":"S12a","setName":"จักรวาลแห่งVSTAR","localId":"112","rarity":"Unknown","imageBase":"","language":"th"}],"705":[{"id":"S12a-113","name":"ฮิซุย นูเมล","dexNumber":705,"setId":"S12a","setName":"จักรวาลแห่งVSTAR","localId":"113","rarity":"Unknown","imageBase":"","language":"th"}],"706":[{"id":"S12a-114","name":"ฮิซุย นูเมลกอน","dexNumber":706,"setId":"S12a","setName":"จักรวาลแห่งVSTAR","localId":"114","rarity":"Unknown","imageBase":"","language":"th"}],"707":[{"id":"SV1V-045","name":"เคลฟฟี","dexNumber":707,"setId":"SV1V","setName":"ไวโอเล็ต ex","localId":"045","rarity":"Rare","imageBase":"","language":"th"},{"id":"SV4a-087","name":"เคลฟฟี","dexNumber":707,"setId":"SV4a","setName":"ไชนีเทรเชอร์ex","localId":"087","rarity":"Unknown","imageBase":"","language":"th"}],"708":[{"id":"SV3-007","name":"โบคุเร","dexNumber":708,"setId":"SV3","setName":"ราชาแห่งเพลิงกาฬ","localId":"007","rarity":"Common","imageBase":"https://assets.tcgdex.net/th/SV/SV3/007","language":"th","hostedThumbUrl":"https://raw.githubusercontent.com/froyonator/pcc-assets-a/main/th/SV3/SV3-007/thumb.webp","hostedFullUrl":"https://raw.githubusercontent.com/froyonator/pcc-assets-a/main/th/SV3/SV3-007/original.webp"},{"id":"SV6-006","name":"โบคุเร","dexNumber":708,"setId":"SV6","setName":"หน้ากากจอมลวงตา","localId":"006","rarity":"Common","imageBase":"","language":"th"}],"709":[{"id":"SV3-008","name":"โอร็อต","dexNumber":709,"setId":"SV3","setName":"ราชาแห่งเพลิงกาฬ","localId":"008","rarity":"Uncommon","imageBase":"https://assets.tcgdex.net/th/SV/SV3/008","language":"th","hostedThumbUrl":"https://raw.githubusercontent.com/froyonator/pcc-assets-a/main/th/SV3/SV3-008/thumb.webp","hostedFullUrl":"https://raw.githubusercontent.com/froyonator/pcc-assets-a/main/th/SV3/SV3-008/original.webp"},{"id":"SV6-007","name":"โอร็อต","dexNumber":709,"setId":"SV6","setName":"หน้ากากจอมลวงตา","localId":"007","rarity":"Common","imageBase":"","language":"th"}],"710":[{"id":"S12a-061","name":"บาเค็จจะ","dexNumber":710,"setId":"S12a","setName":"จักรวาลแห่งVSTAR","localId":"061","rarity":"Unknown","imageBase":"","language":"th"},{"id":"SV4M-029","name":"บาเค็จจะ","dexNumber":710,"setId":"SV4M","setName":"ประกายแสงจากอนาคต","localId":"029","rarity":"Common","imageBase":"","language":"th"}],"711":[{"id":"S12a-062","name":"พัมพ์จิน","dexNumber":711,"setId":"S12a","setName":"จักรวาลแห่งVSTAR","localId":"062","rarity":"Unknown","imageBase":"","language":"th"},{"id":"SV4M-030","name":"พัมพ์จิน","dexNumber":711,"setId":"SV4M","setName":"ประกายแสงจากอนาคต","localId":"030","rarity":"Uncommon","imageBase":"","language":"th"}],"714":[{"id":"S12-073","name":"ออนแบท","dexNumber":714,"setId":"S12","setName":"ปฐมบทแห่งยุคใหม่","localId":"073","rarity":"Common","imageBase":"","language":"th"},{"id":"SV2D-057","name":"ออนแบท","dexNumber":714,"setId":"SV2D","setName":"เคลย์เบิสต์","localId":"057","rarity":"Common","imageBase":"","language":"th"}],"715":[{"id":"S12-074","name":"ออนเวิร์น","dexNumber":715,"setId":"S12","setName":"ปฐมบทแห่งยุคใหม่","localId":"074","rarity":"Uncommon","imageBase":"","language":"th"}],"717":[{"id":"SV3a-039","name":"อีเวลทอล","dexNumber":717,"setId":"SV3a","setName":"คลื่นพิโรธ","localId":"039","rarity":"Rare","imageBase":"","language":"th"},{"id":"SV3a-071","name":"อีเวลทอล","dexNumber":717,"setId":"SV3a","setName":"คลื่นพิโรธ","localId":"071","rarity":"Unknown","imageBase":"","language":"th"}],"718":[{"id":"S12-075","name":"ซีการ์ด","dexNumber":718,"setId":"S12","setName":"ปฐมบทแห่งยุคใหม่","localId":"075","rarity":"Common","imageBase":"","language":"th"}],"719":[{"id":"S12a-063","name":"ดีแอนซี","dexNumber":719,"setId":"S12a","setName":"จักรวาลแห่งVSTAR","localId":"063","rarity":"Unknown","imageBase":"","language":"th"}]}