{"906":[{"id":"SV1a-004","name":"Sprigatito","dexNumber":906,"setId":"SV1a","setName":"Hantaman Triplet","localId":"004","rarity":"Common","imageBase":"https://assets.tcgdex.net/id/SV/SV1a/004","language":"id","hostedThumbUrl":"https://raw.githubusercontent.com/froyonator/pcc-assets-a/main/id/SV1a/SV1a-004/thumb.webp","hostedFullUrl":"https://raw.githubusercontent.com/froyonator/pcc-assets-a/main/id/SV1a/SV1a-004/original.webp"},{"id":"SV1a-005","name":"Sprigatito","dexNumber":906,"setId":"SV1a","setName":"Hantaman Triplet","localId":"005","rarity":"Common","imageBase":"https://assets.tcgdex.net/id/SV/SV1a/005","language":"id","hostedThumbUrl":"https://raw.githubusercontent.com/froyonator/pcc-assets-a/main/id/SV1a/SV1a-005/thumb.webp","hostedFullUrl":"https://raw.githubusercontent.com/froyonator/pcc-assets-a/main/id/SV1a/SV1a-005/original.webp"},{"id":"SV4a-012","name":"Sprigatito","dexNumber":906,"setId":"SV4a","setName":"Harta Berkilau ex","localId":"012","rarity":"Unknown","imageBase":"https://assets.tcgdex.net/id/SV/SV4a/012","language":"id","hostedThumbUrl":"https://raw.githubusercontent.com/froyonator/pcc-assets-a/main/id/SV4a/SV4a-012/thumb.webp","hostedFullUrl":"https://raw.githubusercontent.com/froyonator/pcc-assets-a/main/id/SV4a/SV4a-012/original.webp"},{"id":"SV4a-201","name":"Sprigatito","dexNumber":906,"setId":"SV4a","setName":"Harta Berkilau ex","localId":"201","rarity":"Unknown","imageBase":"","language":"id"}],"907":[{"id":"SV1a-006","name":"Floragato","dexNumber":907,"setId":"SV1a","setName":"Hantaman Triplet","localId":"006","rarity":"Common","imageBase":"https://assets.tcgdex.net/id/SV/SV1a/006","language":"id","hostedThumbUrl":"https://raw.githubusercontent.com/froyonator/pcc-assets-a/main/id/SV1a/SV1a-006/thumb.webp","hostedFullUrl":"https://raw.githubusercontent.com/froyonator/pcc-assets-a/main/id/SV1a/SV1a-006/original.webp"},{"id":"SV4a-013","name":"Floragato","dexNumber":907,"setId":"SV4a","setName":"Harta Berkilau ex","localId":"013","rarity":"Unknown","imageBase":"https://assets.tcgdex.net/id/SV/SV4a/013","language":"id","hostedThumbUrl":"https://raw.githubusercontent.com/froyonator/pcc-assets-a/main/id/SV4a/SV4a-013/thumb.webp","hostedFullUrl":"https://raw.githubusercontent.com/froyonator/pcc-assets-a/main/id/SV4a/SV4a-013/original.webp"},{"id":"SV4a-202","name":"Floragato","dexNumber":907,"setId":"SV4a","setName":"Harta Berkilau ex","localId":"202","rarity":"Unknown","imageBase":"","language":"id"}],"909":[{"id":"SV1a-017","name":"Fuecoco","dexNumber":909,"setId":"SV1a","setName":"Hantaman Triplet","localId":"017","rarity":"Common","imageBase":"https://assets.tcgdex.net/id/SV/SV1a/017","language":"id","hostedThumbUrl":"https://raw.githubusercontent.com/froyonator/pcc-assets-a/main/id/SV1a/SV1a-017/thumb.webp","hostedFullUrl":"https://raw.githubusercontent.com/froyonator/pcc-assets-a/main/id/SV1a/SV1a-017/original.webp"},{"id":"SV1a-018","name":"Fuecoco","dexNumber":909,"setId":"SV1a","setName":"Hantaman Triplet","localId":"018","rarity":"Common","imageBase":"https://assets.tcgdex.net/id/SV/SV1a/018","language":"id","hostedThumbUrl":"https://raw.githubusercontent.com/froyonator/pcc-assets-a/main/id/SV1a/SV1a-018/thumb.webp","hostedFullUrl":"https://raw.githubusercontent.com/froyonator/pcc-assets-a/main/id/SV1a/SV1a-018/original.webp"},{"id":"SV4a-030","name":"Fuecoco","dexNumber":909,"setId":"SV4a","setName":"Harta Berkilau ex","localId":"030","rarity":"Unknown","imageBase":"","language":"id"},{"id":"SV4a-215","name":"Fuecoco","dexNumber":909,"setId":"SV4a","setName":"Harta Berkilau ex","localId":"215","rarity":"Unknown","imageBase":"","language":"id"}],"910":[{"id":"SV1a-019","name":"Crocalor","dexNumber":910,"setId":"SV1a","setName":"Hantaman Triplet","localId":"019","rarity":"Common","imageBase":"https://assets.tcgdex.net/id/SV/SV1a/019","language":"id","hostedThumbUrl":"https://raw.githubusercontent.com/froyonator/pcc-assets-a/main/id/SV1a/SV1a-019/thumb.webp","hostedFullUrl":"https://raw.githubusercontent.com/froyonator/pcc-assets-a/main/id/SV1a/SV1a-019/original.webp"},{"id":"SV4a-031","name":"Crocalor","dexNumber":910,"setId":"SV4a","setName":"Harta Berkilau ex","localId":"031","rarity":"Unknown","imageBase":"","language":"id"},{"id":"SV4a-216","name":"Crocalor","dexNumber":910,"setId":"SV4a","setName":"Harta Berkilau ex","localId":"216","rarity":"Unknown","imageBase":"","language":"id"}],"912":[{"id":"SV1a-027","name":"Quaxly","dexNumber":912,"setId":"SV1a","setName":"Hantaman Triplet","localId":"027","rarity":"Common","imageBase":"","language":"id"},{"id":"SV1a-028","name":"Quaxly","dexNumber":912,"setId":"SV1a","setName":"Hantaman Triplet","localId":"028","rarity":"Common","imageBase":"","language":"id"},{"id":"SV4a-041","name":"Quaxly","dexNumber":912,"setId":"SV4a","setName":"Harta Berkilau ex","localId":"041","rarity":"Unknown","imageBase":"","language":"id"},{"id":"SV4a-224","name":"Quaxly","dexNumber":912,"setId":"SV4a","setName":"Harta Berkilau ex","localId":"224","rarity":"Unknown","imageBase":"","language":"id"}],"913":[{"id":"SV1a-029","name":"Quaxwell","dexNumber":913,"setId":"SV1a","setName":"Hantaman Triplet","localId":"029","rarity":"Common","imageBase":"","language":"id"},{"id":"SV4a-042","name":"Quaxwell","dexNumber":913,"setId":"SV4a","setName":"Harta Berkilau ex","localId":"042","rarity":"Unknown","imageBase":"","language":"id"},{"id":"SV4a-225","name":"Quaxwell","dexNumber":913,"setId":"SV4a","setName":"Harta Berkilau ex","localId":"225","rarity":"Unknown","imageBase":"","language":"id"}],"915":[{"id":"SV1S-066","name":"Lechonk","dexNumber":915,"setId":"SV1S","setName":"Scarlet ex","localId":"066","rarity":"Common","imageBase":"","language":"id"},{"id":"SV1S-067","name":"Lechonk","dexNumber":915,"setId":"SV1S","setName":"Scarlet ex","localId":"067","rarity":"Common","imageBase":"","language":"id"},{"id":"SV4a-315","name":"Lechonk","dexNumber":915,"setId":"SV4a","setName":"Harta Berkilau ex","localId":"315","rarity":"Unknown","imageBase":"","language":"id"}],"916":[{"id":"SV4a-316","name":"Oinkologne","dexNumber":916,"setId":"SV4a","setName":"Harta Berkilau ex","localId":"316","rarity":"Unknown","imageBase":"","language":"id"}],"917":[{"id":"SV1V-006","name":"Tarountula","dexNumber":917,"setId":"SV1V","setName":"Violet ex","localId":"006","rarity":"Common","imageBase":"https://assets.tcgdex.net/id/SV/SV1V/006","language":"id","hostedThumbUrl":"https://raw.githubusercontent.com/froyonator/pcc-assets-a/main/id/SV1V/SV1V-006/thumb.webp","hostedFullUrl":"https://raw.githubusercontent.com/froyonator/pcc-assets-a/main/id/SV1V/SV1V-006/original.webp"},{"id":"SV1V-007","name":"Tarountula","dexNumber":917,"setId":"SV1V","setName":"Violet ex","localId":"007","rarity":"Common","imageBase":"https://assets.tcgdex.net/id/SV/SV1V/007","language":"id","hostedThumbUrl":"https://raw.githubusercontent.com/froyonator/pcc-assets-a/main/id/SV1V/SV1V-007/thumb.webp","hostedFullUrl":"https://raw.githubusercontent.com/froyonator/pcc-assets-a/main/id/SV1V/SV1V-007/original.webp"},{"id":"SV2D-007","name":"Tarountula","dexNumber":917,"setId":"SV2D","setName":"Letusan Tanah","localId":"007","rarity":"Common","imageBase":"https://assets.tcgdex.net/id/SV/SV2D/007","language":"id","hostedThumbUrl":"https://raw.githubusercontent.com/froyonator/pcc-assets-a/main/id/SV2D/SV2D-007/thumb.webp","hostedFullUrl":"https://raw.githubusercontent.com/froyonator/pcc-assets-a/main/id/SV2D/SV2D-007/original.webp"},{"id":"SV2D-008","name":"Tarountula","dexNumber":917,"setId":"SV2D","setName":"Letusan Tanah","localId":"008","rarity":"Common","imageBase":"https://assets.tcgdex.net/id/SV/SV2D/008","language":"id","hostedThumbUrl":"https://raw.githubusercontent.com/froyonator/pcc-assets-a/main/id/SV2D/SV2D-008/thumb.webp","hostedFullUrl":"https://raw.githubusercontent.com/froyonator/pcc-assets-a/main/id/SV2D/SV2D-008/original.webp"}],"918":[{"id":"SV2D-009","name":"Spidops","dexNumber":918,"setId":"SV2D","setName":"Letusan Tanah","localId":"009","rarity":"Uncommon","imageBase":"https://assets.tcgdex.net/id/SV/SV2D/009","language":"id","hostedThumbUrl":"https://raw.githubusercontent.com/froyonator/pcc-assets-a/main/id/SV2D/SV2D-009/thumb.webp","hostedFullUrl":"https://raw.githubusercontent.com/froyonator/pcc-assets-a/main/id/SV2D/SV2D-009/original.webp"}],"919":[{"id":"SV1a-008","name":"Nymble","dexNumber":919,"setId":"SV1a","setName":"Hantaman Triplet","localId":"008","rarity":"Common","imageBase":"https://assets.tcgdex.net/id/SV/SV1a/008","language":"id","hostedThumbUrl":"https://raw.githubusercontent.com/froyonator/pcc-assets-a/main/id/SV1a/SV1a-008/thumb.webp","hostedFullUrl":"https://raw.githubusercontent.com/froyonator/pcc-assets-a/main/id/SV1a/SV1a-008/original.webp"},{"id":"SV1a-009","name":"Nymble","dexNumber":919,"setId":"SV1a","setName":"Hantaman Triplet","localId":"009","rarity":"Common","imageBase":"https://assets.tcgdex.net/id/SV/SV1a/009","language":"id","hostedThumbUrl":"https://raw.githubusercontent.com/froyonator/pcc-assets-a/main/id/SV1a/SV1a-009/thumb.webp","hostedFullUrl":"https://raw.githubusercontent.com/froyonator/pcc-assets-a/main/id/SV1a/SV1a-009/original.webp"}],"920":[{"id":"SV1a-010","name":"Lokix","dexNumber":920,"setId":"SV1a","setName":"Hantaman Triplet","localId":"010","rarity":"Rare","imageBase":"https://assets.tcgdex.net/id/SV/SV1a/010","language":"id","hostedThumbUrl":"https://raw.githubusercontent.com/froyonator/pcc-assets-a/main/id/SV1a/SV1a-010/thumb.webp","hostedFullUrl":"https://raw.githubusercontent.com/froyonator/pcc-assets-a/main/id/SV1a/SV1a-010/original.webp"}],"921":[{"id":"SV1V-033","name":"Pawmi","dexNumber":921,"setId":"SV1V","setName":"Violet ex","localId":"033","rarity":"Common","imageBase":"","language":"id"},{"id":"SV1V-034","name":"Pawmi","dexNumber":921,"setId":"SV1V","setName":"Violet ex","localId":"034","rarity":"Common","imageBase":"","language":"id"},{"id":"SV4a-066","name":"Pawmi","dexNumber":921,"setId":"SV4a","setName":"Harta Berkilau ex","localId":"066","rarity":"Unknown","imageBase":"","language":"id"},{"id":"SV4a-247","name":"Pawmi","dexNumber":921,"setId":"SV4a","setName":"Harta Berkilau ex","localId":"247","rarity":"Unknown","imageBase":"","language":"id"},{"id":"SV4a-340","name":"Pawmi","dexNumber":921,"setId":"SV4a","setName":"Harta Berkilau ex","localId":"340","rarity":"Unknown","imageBase":"","language":"id"}],"922":[{"id":"SV1V-035","name":"Pawmo","dexNumber":922,"setId":"SV1V","setName":"Violet ex","localId":"035","rarity":"Common","imageBase":"","language":"id"},{"id":"SV4a-067","name":"Pawmo","dexNumber":922,"setId":"SV4a","setName":"Harta Berkilau ex","localId":"067","rarity":"Unknown","imageBase":"","language":"id"},{"id":"SV4a-248","name":"Pawmo","dexNumber":922,"setId":"SV4a","setName":"Harta Berkilau ex","localId":"248","rarity":"Unknown","imageBase":"","language":"id"}],"923":[{"id":"SV1V-036","name":"Pawmot","dexNumber":923,"setId":"SV1V","setName":"Violet ex","localId":"036","rarity":"Rare","imageBase":"","language":"id"},{"id":"SV4a-068","name":"Pawmot","dexNumber":923,"setId":"SV4a","setName":"Harta Berkilau ex","localId":"068","rarity":"Unknown","imageBase":"","language":"id"},{"id":"SV4a-249","name":"Pawmot","dexNumber":923,"setId":"SV4a","setName":"Harta Berkilau ex","localId":"249","rarity":"Unknown","imageBase":"","language":"id"}],"924":[{"id":"SV1V-064","name":"Tandemaus","dexNumber":924,"setId":"SV1V","setName":"Violet ex","localId":"064","rarity":"Common","imageBase":"","language":"id"},{"id":"SV1V-065","name":"Tandemaus","dexNumber":924,"setId":"SV1V","setName":"Violet ex","localId":"065","rarity":"Common","imageBase":"","language":"id"},{"id":"SV2D-062","name":"Tandemaus","dexNumber":924,"setId":"SV2D","setName":"Letusan Tanah","localId":"062","rarity":"Common","imageBase":"","language":"id"},{"id":"SV2D-063","name":"Tandemaus","dexNumber":924,"setId":"SV2D","setName":"Letusan Tanah","localId":"063","rarity":"Common","imageBase":"","language":"id"},{"id":"SV4a-317","name":"Tandemaus","dexNumber":924,"setId":"SV4a","setName":"Harta Berkilau ex","localId":"317","rarity":"Unknown","imageBase":"","language":"id"}],"925":[{"id":"SV1V-066","name":"Maushold","dexNumber":925,"setId":"SV1V","setName":"Violet ex","localId":"066","rarity":"Uncommon","imageBase":"","language":"id"},{"id":"SV2D-064","name":"Maushold","dexNumber":925,"setId":"SV2D","setName":"Letusan Tanah","localId":"064","rarity":"Uncommon","imageBase":"","language":"id"},{"id":"SV4a-318","name":"Maushold","dexNumber":925,"setId":"SV4a","setName":"Harta Berkilau ex","localId":"318","rarity":"Unknown","imageBase":"","language":"id"}],"926":[{"id":"SV1S-032","name":"Fidough","dexNumber":926,"setId":"SV1S","setName":"Scarlet ex","localId":"032","rarity":"Common","imageBase":"","language":"id"},{"id":"SV1S-033","name":"Fidough","dexNumber":926,"setId":"SV1S","setName":"Scarlet ex","localId":"033","rarity":"Common","imageBase":"","language":"id"},{"id":"SV4a-089","name":"Fidough","dexNumber":926,"setId":"SV4a","setName":"Harta Berkilau ex","localId":"089","rarity":"Unknown","imageBase":"","language":"id"},{"id":"SV4a-266","name":"Fidough","dexNumber":926,"setId":"SV4a","setName":"Harta Berkilau ex","localId":"266","rarity":"Unknown","imageBase":"","language":"id"}],"927":[{"id":"SV1S-034","name":"Dachsbun","dexNumber":927,"setId":"SV1S","setName":"Scarlet ex","localId":"034","rarity":"Uncommon","imageBase":"","language":"id"},{"id":"SV4a-090","name":"Dachsbun","dexNumber":927,"setId":"SV4a","setName":"Harta Berkilau ex","localId":"090","rarity":"Unknown","imageBase":"","language":"id"},{"id":"SV4a-267","name":"Dachsbun","dexNumber":927,"setId":"SV4a","setName":"Harta Berkilau ex","localId":"267","rarity":"Unknown","imageBase":"","language":"id"}],"928":[{"id":"SV1S-005","name":"Smoliv","dexNumber":928,"setId":"SV1S","setName":"Scarlet ex","localId":"005","rarity":"Common","imageBase":"https://assets.tcgdex.net/id/SV/SV1S/005","language":"id","hostedThumbUrl":"https://raw.githubusercontent.com/froyonator/pcc-assets-a/main/id/SV1S/SV1S-005/thumb.webp","hostedFullUrl":"https://raw.githubusercontent.com/froyonator/pcc-assets-a/main/id/SV1S/SV1S-005/original.webp"},{"id":"SV1S-006","name":"Smoliv","dexNumber":928,"setId":"SV1S","setName":"Scarlet ex","localId":"006","rarity":"Common","imageBase":"https://assets.tcgdex.net/id/SV/SV1S/006","language":"id","hostedThumbUrl":"https://raw.githubusercontent.com/froyonator/pcc-assets-a/main/id/SV1S/SV1S-006/thumb.webp","hostedFullUrl":"https://raw.githubusercontent.com/froyonator/pcc-assets-a/main/id/SV1S/SV1S-006/original.webp"},{"id":"SV4a-015","name":"Smoliv","dexNumber":928,"setId":"SV4a","setName":"Harta Berkilau ex","localId":"015","rarity":"Unknown","imageBase":"https://assets.tcgdex.net/id/SV/SV4a/015","language":"id","hostedThumbUrl":"https://raw.githubusercontent.com/froyonator/pcc-assets-a/main/id/SV4a/SV4a-015/thumb.webp","hostedFullUrl":"https://raw.githubusercontent.com/froyonator/pcc-assets-a/main/id/SV4a/SV4a-015/original.webp"},{"id":"SV4a-203","name":"Smoliv","dexNumber":928,"setId":"SV4a","setName":"Harta Berkilau ex","localId":"203","rarity":"Unknown","imageBase":"","language":"id"}],"929":[{"id":"SV1S-007","name":"Dolliv","dexNumber":929,"setId":"SV1S","setName":"Scarlet ex","localId":"007","rarity":"Common","imageBase":"https://assets.tcgdex.net/id/SV/SV1S/007","language":"id","hostedThumbUrl":"https://raw.githubusercontent.com/froyonator/pcc-assets-a/main/id/SV1S/SV1S-007/thumb.webp","hostedFullUrl":"https://raw.githubusercontent.com/froyonator/pcc-assets-a/main/id/SV1S/SV1S-007/original.webp"},{"id":"SV4a-016","name":"Dolliv","dexNumber":929,"setId":"SV4a","setName":"Harta Berkilau ex","localId":"016","rarity":"Unknown","imageBase":"https://assets.tcgdex.net/id/SV/SV4a/016","language":"id","hostedThumbUrl":"https://raw.githubusercontent.com/froyonator/pcc-assets-a/main/id/SV4a/SV4a-016/thumb.webp","hostedFullUrl":"https://raw.githubusercontent.com/froyonator/pcc-assets-a/main/id/SV4a/SV4a-016/original.webp"},{"id":"SV4a-204","name":"Dolliv","dexNumber":929,"setId":"SV4a","setName":"Harta Berkilau ex","localId":"204","rarity":"Unknown","imageBase":"","language":"id"}],"930":[{"id":"SV1S-008","name":"Arboliva","dexNumber":930,"setId":"SV1S","setName":"Scarlet ex","localId":"008","rarity":"Rare","imageBase":"https://assets.tcgdex.net/id/SV/SV1S/008","language":"id","hostedThumbUrl":"https://raw.githubusercontent.com/froyonator/pcc-assets-a/main/id/SV1S/SV1S-008/thumb.webp","hostedFullUrl":"https://raw.githubusercontent.com/froyonator/pcc-assets-a/main/id/SV1S/SV1S-008/original.webp"},{"id":"SV4a-017","name":"Arboliva","dexNumber":930,"setId":"SV4a","setName":"Harta Berkilau ex","localId":"017","rarity":"Unknown","imageBase":"https://assets.tcgdex.net/id/SV/SV4a/017","language":"id","hostedThumbUrl":"https://raw.githubusercontent.com/froyonator/pcc-assets-a/main/id/SV4a/SV4a-017/thumb.webp","hostedFullUrl":"https://raw.githubusercontent.com/froyonator/pcc-assets-a/main/id/SV4a/SV4a-017/original.webp"},{"id":"SV4a-205","name":"Arboliva","dexNumber":930,"setId":"SV4a","setName":"Harta Berkilau ex","localId":"205","rarity":"Unknown","imageBase":"","language":"id"}],"931":[{"id":"SV1V-067","name":"Squawkabilly","dexNumber":931,"setId":"SV1V","setName":"Violet ex","localId":"067","rarity":"Common","imageBase":"","language":"id"}],"932":[{"id":"SV2D-045","name":"Nacli","dexNumber":932,"setId":"SV2D","setName":"Letusan Tanah","localId":"045","rarity":"Common","imageBase":"","language":"id"},{"id":"SV2D-046","name":"Nacli","dexNumber":932,"setId":"SV2D","setName":"Letusan Tanah","localId":"046","rarity":"Common","imageBase":"","language":"id"},{"id":"SV4a-107","name":"Nacli","dexNumber":932,"setId":"SV4a","setName":"Harta Berkilau ex","localId":"107","rarity":"Unknown","imageBase":"","language":"id"},{"id":"SV4a-283","name":"Nacli","dexNumber":932,"setId":"SV4a","setName":"Harta Berkilau ex","localId":"283","rarity":"Unknown","imageBase":"","language":"id"}],"933":[{"id":"SV2D-047","name":"Naclstack","dexNumber":933,"setId":"SV2D","setName":"Letusan Tanah","localId":"047","rarity":"Common","imageBase":"","language":"id"},{"id":"SV4a-108","name":"Naclstack","dexNumber":933,"setId":"SV4a","setName":"Harta Berkilau ex","localId":"108","rarity":"Unknown","imageBase":"","language":"id"},{"id":"SV4a-284","name":"Naclstack","dexNumber":933,"setId":"SV4a","setName":"Harta Berkilau ex","localId":"284","rarity":"Unknown","imageBase":"","language":"id"}],"934":[{"id":"SV2D-048","name":"Garganacl","dexNumber":934,"setId":"SV2D","setName":"Letusan Tanah","localId":"048","rarity":"Rare","imageBase":"","language":"id"},{"id":"SV4a-109","name":"Garganacl","dexNumber":934,"setId":"SV4a","setName":"Harta Berkilau ex","localId":"109","rarity":"Unknown","imageBase":"","language":"id"},{"id":"SV4a-285","name":"Garganacl","dexNumber":934,"setId":"SV4a","setName":"Harta Berkilau ex","localId":"285","rarity":"Unknown","imageBase":"","language":"id"}],"935":[{"id":"SV1S-010","name":"Charcadet","dexNumber":935,"setId":"SV1S","setName":"Scarlet ex","localId":"010","rarity":"Common","imageBase":"https://assets.tcgdex.net/id/SV/SV1S/010","language":"id","hostedThumbUrl":"https://raw.githubusercontent.com/froyonator/pcc-assets-a/main/id/SV1S/SV1S-010/thumb.webp","hostedFullUrl":"https://raw.githubusercontent.com/froyonator/pcc-assets-a/main/id/SV1S/SV1S-010/original.webp"},{"id":"SV1S-011","name":"Charcadet","dexNumber":935,"setId":"SV1S","setName":"Scarlet ex","localId":"011","rarity":"Common","imageBase":"https://assets.tcgdex.net/id/SV/SV1S/011","language":"id","hostedThumbUrl":"https://raw.githubusercontent.com/froyonator/pcc-assets-a/main/id/SV1S/SV1S-011/thumb.webp","hostedFullUrl":"https://raw.githubusercontent.com/froyonator/pcc-assets-a/main/id/SV1S/SV1S-011/original.webp"},{"id":"SV2D-014","name":"Charcadet","dexNumber":935,"setId":"SV2D","setName":"Letusan Tanah","localId":"014","rarity":"Common","imageBase":"https://assets.tcgdex.net/id/SV/SV2D/014","language":"id","hostedThumbUrl":"https://raw.githubusercontent.com/froyonator/pcc-assets-a/main/id/SV2D/SV2D-014/thumb.webp","hostedFullUrl":"https://raw.githubusercontent.com/froyonator/pcc-assets-a/main/id/SV2D/SV2D-014/original.webp"},{"id":"SV2D-015","name":"Charcadet","dexNumber":935,"setId":"SV2D","setName":"Letusan Tanah","localId":"015","rarity":"Common","imageBase":"https://assets.tcgdex.net/id/SV/SV2D/015","language":"id","hostedThumbUrl":"https://raw.githubusercontent.com/froyonator/pcc-assets-a/main/id/SV2D/SV2D-015/thumb.webp","hostedFullUrl":"https://raw.githubusercontent.com/froyonator/pcc-assets-a/main/id/SV2D/SV2D-015/original.webp"},{"id":"SV4a-033","name":"Charcadet","dexNumber":935,"setId":"SV4a","setName":"Harta Berkilau ex","localId":"033","rarity":"Unknown","imageBase":"","language":"id"},{"id":"SV4a-217","name":"Charcadet","dexNumber":935,"setId":"SV4a","setName":"Harta Berkilau ex","localId":"217","rarity":"Unknown","imageBase":"","language":"id"},{"id":"SV8a-023","name":"Charcadet","dexNumber":935,"setId":"SV8a","setName":"Festival Terastal ex","localId":"023","rarity":"None","imageBase":"https://assets.tcgdex.net/id/SV/SV8a/023","language":"id","hostedThumbUrl":"https://raw.githubusercontent.com/froyonator/pcc-assets-a/main/id/SV8a/SV8a-023/thumb.webp","hostedFullUrl":"https://raw.githubusercontent.com/froyonator/pcc-assets-a/main/id/SV8a/SV8a-023/original.webp"}],"936":[{"id":"SV1S-012","name":"Armarouge","dexNumber":936,"setId":"SV1S","setName":"Scarlet ex","localId":"012","rarity":"Rare","imageBase":"https://assets.tcgdex.net/id/SV/SV1S/012","language":"id","hostedThumbUrl":"https://raw.githubusercontent.com/froyonator/pcc-assets-a/main/id/SV1S/SV1S-012/thumb.webp","hostedFullUrl":"https://raw.githubusercontent.com/froyonator/pcc-assets-a/main/id/SV1S/SV1S-012/original.webp"},{"id":"SV4a-034","name":"Armarouge","dexNumber":936,"setId":"SV4a","setName":"Harta Berkilau ex","localId":"034","rarity":"Unknown","imageBase":"","language":"id"},{"id":"SV4a-218","name":"Armarouge","dexNumber":936,"setId":"SV4a","setName":"Harta Berkilau ex","localId":"218","rarity":"Unknown","imageBase":"","language":"id"}],"937":[{"id":"SV2D-031","name":"Ceruledge","dexNumber":937,"setId":"SV2D","setName":"Letusan Tanah","localId":"031","rarity":"Rare","imageBase":"","language":"id"},{"id":"SV4a-091","name":"Ceruledge","dexNumber":937,"setId":"SV4a","setName":"Harta Berkilau ex","localId":"091","rarity":"Unknown","imageBase":"","language":"id"},{"id":"SV4a-268","name":"Ceruledge","dexNumber":937,"setId":"SV4a","setName":"Harta Berkilau ex","localId":"268","rarity":"Unknown","imageBase":"","language":"id"},{"id":"SV8a-070","name":"Ceruledge","dexNumber":937,"setId":"SV8a","setName":"Festival Terastal ex","localId":"070","rarity":"None","imageBase":"https://assets.tcgdex.net/id/SV/SV8a/070","language":"id","hostedThumbUrl":"https://raw.githubusercontent.com/froyonator/pcc-assets-a/main/id/SV8a/SV8a-070/thumb.webp","hostedFullUrl":"https://raw.githubusercontent.com/froyonator/pcc-assets-a/main/id/SV8a/SV8a-070/original.webp"}],"938":[{"id":"SV2D-023","name":"Tadbulb","dexNumber":938,"setId":"SV2D","setName":"Letusan Tanah","localId":"023","rarity":"Common","imageBase":"","language":"id"},{"id":"SV2D-024","name":"Tadbulb","dexNumber":938,"setId":"SV2D","setName":"Letusan Tanah","localId":"024","rarity":"Common","imageBase":"","language":"id"}],"940":[{"id":"SV1a-031","name":"Wattrel","dexNumber":940,"setId":"SV1a","setName":"Hantaman Triplet","localId":"031","rarity":"Common","imageBase":"","language":"id"},{"id":"SV1a-032","name":"Wattrel","dexNumber":940,"setId":"SV1a","setName":"Hantaman Triplet","localId":"032","rarity":"Common","imageBase":"","language":"id"},{"id":"SV1S-023","name":"Wattrel","dexNumber":940,"setId":"SV1S","setName":"Scarlet ex","localId":"023","rarity":"Common","imageBase":"","language":"id"},{"id":"SV1S-024","name":"Wattrel","dexNumber":940,"setId":"SV1S","setName":"Scarlet ex","localId":"024","rarity":"Common","imageBase":"","language":"id"},{"id":"SV4a-069","name":"Wattrel","dexNumber":940,"setId":"SV4a","setName":"Harta Berkilau ex","localId":"069","rarity":"Unknown","imageBase":"","language":"id"},{"id":"SV4a-250","name":"Wattrel","dexNumber":940,"setId":"SV4a","setName":"Harta Berkilau ex","localId":"250","rarity":"Unknown","imageBase":"","language":"id"}],"941":[{"id":"SV1a-033","name":"Kilowattrel","dexNumber":941,"setId":"SV1a","setName":"Hantaman Triplet","localId":"033","rarity":"Uncommon","imageBase":"","language":"id"},{"id":"SV1S-025","name":"Kilowattrel","dexNumber":941,"setId":"SV1S","setName":"Scarlet ex","localId":"025","rarity":"Uncommon","imageBase":"","language":"id"},{"id":"SV4a-070","name":"Kilowattrel","dexNumber":941,"setId":"SV4a","setName":"Harta Berkilau ex","localId":"070","rarity":"Unknown","imageBase":"","language":"id"},{"id":"SV4a-251","name":"Kilowattrel","dexNumber":941,"setId":"SV4a","setName":"Harta Berkilau ex","localId":"251","rarity":"Unknown","imageBase":"","language":"id"}],"942":[{"id":"SV1V-053","name":"Maschiff","dexNumber":942,"setId":"SV1V","setName":"Violet ex","localId":"053","rarity":"Common","imageBase":"","language":"id"},{"id":"SV1V-054","name":"Maschiff","dexNumber":942,"setId":"SV1V","setName":"Violet ex","localId":"054","rarity":"Common","imageBase":"","language":"id"},{"id":"SV2P-047","name":"Maschiff","dexNumber":942,"setId":"SV2P","setName":"Mara Bahaya Salju","localId":"047","rarity":"Common","imageBase":"","language":"id"},{"id":"SV2P-048","name":"Maschiff","dexNumber":942,"setId":"SV2P","setName":"Mara Bahaya Salju","localId":"048","rarity":"Common","imageBase":"","language":"id"},{"id":"SV4a-125","name":"Maschiff","dexNumber":942,"setId":"SV4a","setName":"Harta Berkilau ex","localId":"125","rarity":"Unknown","imageBase":"","language":"id"},{"id":"SV4a-295","name":"Maschiff","dexNumber":942,"setId":"SV4a","setName":"Harta Berkilau ex","localId":"295","rarity":"Unknown","imageBase":"","language":"id"}],"943":[{"id":"SV1V-055","name":"Mabosstiff","dexNumber":943,"setId":"SV1V","setName":"Violet ex","localId":"055","rarity":"Uncommon","imageBase":"","language":"id"},{"id":"SV2P-049","name":"Mabosstiff","dexNumber":943,"setId":"SV2P","setName":"Mara Bahaya Salju","localId":"049","rarity":"Uncommon","imageBase":"","language":"id"},{"id":"SV4a-126","name":"Mabosstiff","dexNumber":943,"setId":"SV4a","setName":"Harta Berkilau ex","localId":"126","rarity":"Unknown","imageBase":"","language":"id"},{"id":"SV4a-296","name":"Mabosstiff","dexNumber":943,"setId":"SV4a","setName":"Harta Berkilau ex","localId":"296","rarity":"Unknown","imageBase":"","language":"id"}],"944":[{"id":"SV2D-053","name":"Shroodle","dexNumber":944,"setId":"SV2D","setName":"Letusan Tanah","localId":"053","rarity":"Common","imageBase":"","language":"id"},{"id":"SV2D-054","name":"Shroodle","dexNumber":944,"setId":"SV2D","setName":"Letusan Tanah","localId":"054","rarity":"Common","imageBase":"","language":"id"},{"id":"SV4a-297","name":"Shroodle","dexNumber":944,"setId":"SV4a","setName":"Harta Berkilau ex","localId":"297","rarity":"Unknown","imageBase":"","language":"id"}],"945":[{"id":"SV2D-055","name":"Grafaiai","dexNumber":945,"setId":"SV2D","setName":"Letusan Tanah","localId":"055","rarity":"Uncommon","imageBase":"","language":"id"},{"id":"SV4a-298","name":"Grafaiai","dexNumber":945,"setId":"SV4a","setName":"Harta Berkilau ex","localId":"298","rarity":"Unknown","imageBase":"","language":"id"}],"946":[{"id":"SV2P-010","name":"Bramblin","dexNumber":946,"setId":"SV2P","setName":"Mara Bahaya Salju","localId":"010","rarity":"Common","imageBase":"https://assets.tcgdex.net/id/SV/SV2P/010","language":"id","hostedThumbUrl":"https://raw.githubusercontent.com/froyonator/pcc-assets-a/main/id/SV2P/SV2P-010/thumb.webp","hostedFullUrl":"https://raw.githubusercontent.com/froyonator/pcc-assets-a/main/id/SV2P/SV2P-010/original.webp"},{"id":"SV2P-011","name":"Bramblin","dexNumber":946,"setId":"SV2P","setName":"Mara Bahaya Salju","localId":"011","rarity":"Common","imageBase":"https://assets.tcgdex.net/id/SV/SV2P/011","language":"id","hostedThumbUrl":"https://raw.githubusercontent.com/froyonator/pcc-assets-a/main/id/SV2P/SV2P-011/thumb.webp","hostedFullUrl":"https://raw.githubusercontent.com/froyonator/pcc-assets-a/main/id/SV2P/SV2P-011/original.webp"},{"id":"SV8a-011","name":"Bramblin","dexNumber":946,"setId":"SV8a","setName":"Festival Terastal ex","localId":"011","rarity":"None","imageBase":"https://assets.tcgdex.net/id/SV/SV8a/011","language":"id","hostedThumbUrl":"https://raw.githubusercontent.com/froyonator/pcc-assets-a/main/id/SV8a/SV8a-011/thumb.webp","hostedFullUrl":"https://raw.githubusercontent.com/froyonator/pcc-assets-a/main/id/SV8a/SV8a-011/original.webp"}],"947":[{"id":"SV2P-012","name":"Brambleghast","dexNumber":947,"setId":"SV2P","setName":"Mara Bahaya Salju","localId":"012","rarity":"Uncommon","imageBase":"https://assets.tcgdex.net/id/SV/SV2P/012","language":"id","hostedThumbUrl":"https://raw.githubusercontent.com/froyonator/pcc-assets-a/main/id/SV2P/SV2P-012/thumb.webp","hostedFullUrl":"https://raw.githubusercontent.com/froyonator/pcc-assets-a/main/id/SV2P/SV2P-012/original.webp"},{"id":"SV8a-012","name":"Brambleghast","dexNumber":947,"setId":"SV8a","setName":"Festival Terastal ex","localId":"012","rarity":"None","imageBase":"https://assets.tcgdex.net/id/SV/SV8a/012","language":"id","hostedThumbUrl":"https://raw.githubusercontent.com/froyonator/pcc-assets-a/main/id/SV8a/SV8a-012/thumb.webp","hostedFullUrl":"https://raw.githubusercontent.com/froyonator/pcc-assets-a/main/id/SV8a/SV8a-012/original.webp"}],"948":[{"id":"SV1V-009","name":"Toedscool","dexNumber":948,"setId":"SV1V","setName":"Violet ex","localId":"009","rarity":"Common","imageBase":"https://assets.tcgdex.net/id/SV/SV1V/009","language":"id","hostedThumbUrl":"https://raw.githubusercontent.com/froyonator/pcc-assets-a/main/id/SV1V/SV1V-009/thumb.webp","hostedFullUrl":"https://raw.githubusercontent.com/froyonator/pcc-assets-a/main/id/SV1V/SV1V-009/original.webp"},{"id":"SV1V-010","name":"Toedscool","dexNumber":948,"setId":"SV1V","setName":"Violet ex","localId":"010","rarity":"Common","imageBase":"https://assets.tcgdex.net/id/SV/SV1V/010","language":"id","hostedThumbUrl":"https://raw.githubusercontent.com/froyonator/pcc-assets-a/main/id/SV1V/SV1V-010/thumb.webp","hostedFullUrl":"https://raw.githubusercontent.com/froyonator/pcc-assets-a/main/id/SV1V/SV1V-010/original.webp"},{"id":"SV4a-018","name":"Toedscool","dexNumber":948,"setId":"SV4a","setName":"Harta Berkilau ex","localId":"018","rarity":"Unknown","imageBase":"https://assets.tcgdex.net/id/SV/SV4a/018","language":"id","hostedThumbUrl":"https://raw.githubusercontent.com/froyonator/pcc-assets-a/main/id/SV4a/SV4a-018/thumb.webp","hostedFullUrl":"https://raw.githubusercontent.com/froyonator/pcc-assets-a/main/id/SV4a/SV4a-018/original.webp"},{"id":"SV4a-206","name":"Toedscool","dexNumber":948,"setId":"SV4a","setName":"Harta Berkilau ex","localId":"206","rarity":"Unknown","imageBase":"","language":"id"}],"949":[{"id":"SV1V-011","name":"Toedscruel","dexNumber":949,"setId":"SV1V","setName":"Violet ex","localId":"011","rarity":"Uncommon","imageBase":"https://assets.tcgdex.net/id/SV/SV1V/011","language":"id","hostedThumbUrl":"https://raw.githubusercontent.com/froyonator/pcc-assets-a/main/id/SV1V/SV1V-011/thumb.webp","hostedFullUrl":"https://raw.githubusercontent.com/froyonator/pcc-assets-a/main/id/SV1V/SV1V-011/original.webp"}],"950":[{"id":"SV1S-048","name":"Klawf","dexNumber":950,"setId":"SV1S","setName":"Scarlet ex","localId":"048","rarity":"Rare","imageBase":"","language":"id"}],"951":[{"id":"SV1V-012","name":"Capsakid","dexNumber":951,"setId":"SV1V","setName":"Violet ex","localId":"012","rarity":"Common","imageBase":"https://assets.tcgdex.net/id/SV/SV1V/012","language":"id","hostedThumbUrl":"https://raw.githubusercontent.com/froyonator/pcc-assets-a/main/id/SV1V/SV1V-012/thumb.webp","hostedFullUrl":"https://raw.githubusercontent.com/froyonator/pcc-assets-a/main/id/SV1V/SV1V-012/original.webp"},{"id":"SV1V-013","name":"Capsakid","dexNumber":951,"setId":"SV1V","setName":"Violet ex","localId":"013","rarity":"Common","imageBase":"https://assets.tcgdex.net/id/SV/SV1V/013","language":"id","hostedThumbUrl":"https://raw.githubusercontent.com/froyonator/pcc-assets-a/main/id/SV1V/SV1V-013/thumb.webp","hostedFullUrl":"https://raw.githubusercontent.com/froyonator/pcc-assets-a/main/id/SV1V/SV1V-013/original.webp"},{"id":"SV4a-020","name":"Capsakid","dexNumber":951,"setId":"SV4a","setName":"Harta Berkilau ex","localId":"020","rarity":"Unknown","imageBase":"https://assets.tcgdex.net/id/SV/SV4a/020","language":"id","hostedThumbUrl":"https://raw.githubusercontent.com/froyonator/pcc-assets-a/main/id/SV4a/SV4a-020/thumb.webp","hostedFullUrl":"https://raw.githubusercontent.com/froyonator/pcc-assets-a/main/id/SV4a/SV4a-020/original.webp"},{"id":"SV4a-207","name":"Capsakid","dexNumber":951,"setId":"SV4a","setName":"Harta Berkilau ex","localId":"207","rarity":"Unknown","imageBase":"","language":"id"}],"952":[{"id":"SV1V-014","name":"Scovillain","dexNumber":952,"setId":"SV1V","setName":"Violet ex","localId":"014","rarity":"Uncommon","imageBase":"https://assets.tcgdex.net/id/SV/SV1V/014","language":"id","hostedThumbUrl":"https://raw.githubusercontent.com/froyonator/pcc-assets-a/main/id/SV1V/SV1V-014/thumb.webp","hostedFullUrl":"https://raw.githubusercontent.com/froyonator/pcc-assets-a/main/id/SV1V/SV1V-014/original.webp"},{"id":"SV4a-021","name":"Scovillain","dexNumber":952,"setId":"SV4a","setName":"Harta Berkilau ex","localId":"021","rarity":"Unknown","imageBase":"","language":"id"},{"id":"SV4a-208","name":"Scovillain","dexNumber":952,"setId":"SV4a","setName":"Harta Berkilau ex","localId":"208","rarity":"Unknown","imageBase":"","language":"id"}],"953":[{"id":"SV2P-013","name":"Rellor","dexNumber":953,"setId":"SV2P","setName":"Mara Bahaya Salju","localId":"013","rarity":"Common","imageBase":"https://assets.tcgdex.net/id/SV/SV2P/013","language":"id","hostedThumbUrl":"https://raw.githubusercontent.com/froyonator/pcc-assets-a/main/id/SV2P/SV2P-013/thumb.webp","hostedFullUrl":"https://raw.githubusercontent.com/froyonator/pcc-assets-a/main/id/SV2P/SV2P-013/original.webp"},{"id":"SV2P-014","name":"Rellor","dexNumber":953,"setId":"SV2P","setName":"Mara Bahaya Salju","localId":"014","rarity":"Common","imageBase":"https://assets.tcgdex.net/id/SV/SV2P/014","language":"id","hostedThumbUrl":"https://raw.githubusercontent.com/froyonator/pcc-assets-a/main/id/SV2P/SV2P-014/thumb.webp","hostedFullUrl":"https://raw.githubusercontent.com/froyonator/pcc-assets-a/main/id/SV2P/SV2P-014/original.webp"},{"id":"SV4a-022","name":"Rellor","dexNumber":953,"setId":"SV4a","setName":"Harta Berkilau ex","localId":"022","rarity":"Unknown","imageBase":"","language":"id"},{"id":"SV4a-209","name":"Rellor","dexNumber":953,"setId":"SV4a","setName":"Harta Berkilau ex","localId":"209","rarity":"Unknown","imageBase":"","language":"id"},{"id":"SV8a-013","name":"Rellor","dexNumber":953,"setId":"SV8a","setName":"Festival Terastal ex","localId":"013","rarity":"None","imageBase":"https://assets.tcgdex.net/id/SV/SV8a/013","language":"id","hostedThumbUrl":"https://raw.githubusercontent.com/froyonator/pcc-assets-a/main/id/SV8a/SV8a-013/thumb.webp","hostedFullUrl":"https://raw.githubusercontent.com/froyonator/pcc-assets-a/main/id/SV8a/SV8a-013/original.webp"}],"954":[{"id":"SV2P-037","name":"Rabsca","dexNumber":954,"setId":"SV2P","setName":"Mara Bahaya Salju","localId":"037","rarity":"Rare","imageBase":"","language":"id"},{"id":"SV4a-092","name":"Rabsca","dexNumber":954,"setId":"SV4a","setName":"Harta Berkilau ex","localId":"092","rarity":"Unknown","imageBase":"","language":"id"},{"id":"SV4a-269","name":"Rabsca","dexNumber":954,"setId":"SV4a","setName":"Harta Berkilau ex","localId":"269","rarity":"Unknown","imageBase":"","language":"id"},{"id":"SV8a-014","name":"Rabsca","dexNumber":954,"setId":"SV8a","setName":"Festival Terastal ex","localId":"014","rarity":"None","imageBase":"https://assets.tcgdex.net/id/SV/SV8a/014","language":"id","hostedThumbUrl":"https://raw.githubusercontent.com/froyonator/pcc-assets-a/main/id/SV8a/SV8a-014/thumb.webp","hostedFullUrl":"https://raw.githubusercontent.com/froyonator/pcc-assets-a/main/id/SV8a/SV8a-014/original.webp"}],"955":[{"id":"SV1S-035","name":"Flittle","dexNumber":955,"setId":"SV1S","setName":"Scarlet ex","localId":"035","rarity":"Common","imageBase":"","language":"id"},{"id":"SV1S-036","name":"Flittle","dexNumber":955,"setId":"SV1S","setName":"Scarlet ex","localId":"036","rarity":"Common","imageBase":"","language":"id"},{"id":"SV4a-093","name":"Flittle","dexNumber":955,"setId":"SV4a","setName":"Harta Berkilau ex","localId":"093","rarity":"Unknown","imageBase":"","language":"id"},{"id":"SV4a-270","name":"Flittle","dexNumber":955,"setId":"SV4a","setName":"Harta Berkilau ex","localId":"270","rarity":"Unknown","imageBase":"","language":"id"}],"956":[{"id":"SV1S-037","name":"Espathra","dexNumber":956,"setId":"SV1S","setName":"Scarlet ex","localId":"037","rarity":"Uncommon","imageBase":"","language":"id"}],"957":[{"id":"SV1a-040","name":"Tinkatink","dexNumber":957,"setId":"SV1a","setName":"Hantaman Triplet","localId":"040","rarity":"Common","imageBase":"","language":"id"},{"id":"SV1a-041","name":"Tinkatink","dexNumber":957,"setId":"SV1a","setName":"Hantaman Triplet","localId":"041","rarity":"Common","imageBase":"","language":"id"},{"id":"SV2D-032","name":"Tinkatink","dexNumber":957,"setId":"SV2D","setName":"Letusan Tanah","localId":"032","rarity":"Common","imageBase":"","language":"id"},{"id":"SV2D-033","name":"Tinkatink","dexNumber":957,"setId":"SV2D","setName":"Letusan Tanah","localId":"033","rarity":"Common","imageBase":"","language":"id"},{"id":"SV4a-094","name":"Tinkatink","dexNumber":957,"setId":"SV4a","setName":"Harta Berkilau ex","localId":"094","rarity":"Unknown","imageBase":"","language":"id"},{"id":"SV4a-271","name":"Tinkatink","dexNumber":957,"setId":"SV4a","setName":"Harta Berkilau ex","localId":"271","rarity":"Unknown","imageBase":"","language":"id"}],"958":[{"id":"SV1a-042","name":"Tinkatuff","dexNumber":958,"setId":"SV1a","setName":"Hantaman Triplet","localId":"042","rarity":"Common","imageBase":"","language":"id"},{"id":"SV2D-034","name":"Tinkatuff","dexNumber":958,"setId":"SV2D","setName":"Letusan Tanah","localId":"034","rarity":"Common","imageBase":"","language":"id"},{"id":"SV4a-095","name":"Tinkatuff","dexNumber":958,"setId":"SV4a","setName":"Harta Berkilau ex","localId":"095","rarity":"Unknown","imageBase":"","language":"id"},{"id":"SV4a-272","name":"Tinkatuff","dexNumber":958,"setId":"SV4a","setName":"Harta Berkilau ex","localId":"272","rarity":"Unknown","imageBase":"","language":"id"}],"959":[{"id":"SV1a-043","name":"Tinkaton","dexNumber":959,"setId":"SV1a","setName":"Hantaman Triplet","localId":"043","rarity":"Rare","imageBase":"","language":"id"},{"id":"SV4a-096","name":"Tinkaton","dexNumber":959,"setId":"SV4a","setName":"Harta Berkilau ex","localId":"096","rarity":"Unknown","imageBase":"","language":"id"},{"id":"SV4a-273","name":"Tinkaton","dexNumber":959,"setId":"SV4a","setName":"Harta Berkilau ex","localId":"273","rarity":"Unknown","imageBase":"","language":"id"}],"960":[{"id":"SV1S-018","name":"Wiglett","dexNumber":960,"setId":"SV1S","setName":"Scarlet ex","localId":"018","rarity":"Common","imageBase":"https://assets.tcgdex.net/id/SV/SV1S/018","language":"id","hostedThumbUrl":"https://raw.githubusercontent.com/froyonator/pcc-assets-a/main/id/SV1S/SV1S-018/thumb.webp","hostedFullUrl":"https://raw.githubusercontent.com/froyonator/pcc-assets-a/main/id/SV1S/SV1S-018/original.webp"},{"id":"SV1S-019","name":"Wiglett","dexNumber":960,"setId":"SV1S","setName":"Scarlet ex","localId":"019","rarity":"Common","imageBase":"https://assets.tcgdex.net/id/SV/SV1S/019","language":"id","hostedThumbUrl":"https://raw.githubusercontent.com/froyonator/pcc-assets-a/main/id/SV1S/SV1S-019/thumb.webp","hostedFullUrl":"https://raw.githubusercontent.com/froyonator/pcc-assets-a/main/id/SV1S/SV1S-019/original.webp"},{"id":"SV4a-044","name":"Wiglett","dexNumber":960,"setId":"SV4a","setName":"Harta Berkilau ex","localId":"044","rarity":"Unknown","imageBase":"","language":"id"},{"id":"SV4a-226","name":"Wiglett","dexNumber":960,"setId":"SV4a","setName":"Harta Berkilau ex","localId":"226","rarity":"Unknown","imageBase":"","language":"id"},{"id":"SV8a-042","name":"Wiglett","dexNumber":960,"setId":"SV8a","setName":"Festival Terastal ex","localId":"042","rarity":"None","imageBase":"https://assets.tcgdex.net/id/SV/SV8a/042","language":"id","hostedThumbUrl":"https://raw.githubusercontent.com/froyonator/pcc-assets-a/main/id/SV8a/SV8a-042/thumb.webp","hostedFullUrl":"https://raw.githubusercontent.com/froyonator/pcc-assets-a/main/id/SV8a/SV8a-042/original.webp"}],"961":[{"id":"SV1S-020","name":"Wugtrio","dexNumber":961,"setId":"SV1S","setName":"Scarlet ex","localId":"020","rarity":"Uncommon","imageBase":"https://assets.tcgdex.net/id/SV/SV1S/020","language":"id","hostedThumbUrl":"https://raw.githubusercontent.com/froyonator/pcc-assets-a/main/id/SV1S/SV1S-020/thumb.webp","hostedFullUrl":"https://raw.githubusercontent.com/froyonator/pcc-assets-a/main/id/SV1S/SV1S-020/original.webp"},{"id":"SV4a-045","name":"Wugtrio","dexNumber":961,"setId":"SV4a","setName":"Harta Berkilau ex","localId":"045","rarity":"Unknown","imageBase":"","language":"id"},{"id":"SV4a-227","name":"Wugtrio","dexNumber":961,"setId":"SV4a","setName":"Harta Berkilau ex","localId":"227","rarity":"Unknown","imageBase":"","language":"id"},{"id":"SV4a-338","name":"Wugtrio","dexNumber":961,"setId":"SV4a","setName":"Harta Berkilau ex","localId":"338","rarity":"Unknown","imageBase":"","language":"id"},{"id":"SV8a-043","name":"Wugtrio","dexNumber":961,"setId":"SV8a","setName":"Festival Terastal ex","localId":"043","rarity":"None","imageBase":"https://assets.tcgdex.net/id/SV/SV8a/043","language":"id","hostedThumbUrl":"https://raw.githubusercontent.com/froyonator/pcc-assets-a/main/id/SV8a/SV8a-043/thumb.webp","hostedFullUrl":"https://raw.githubusercontent.com/froyonator/pcc-assets-a/main/id/SV8a/SV8a-043/original.webp"}],"962":[{"id":"SV1V-056","name":"Bombirdier","dexNumber":962,"setId":"SV1V","setName":"Violet ex","localId":"056","rarity":"Uncommon","imageBase":"","language":"id"},{"id":"SV2D-056","name":"Bombirdier","dexNumber":962,"setId":"SV2D","setName":"Letusan Tanah","localId":"056","rarity":"Uncommon","imageBase":"","language":"id"}],"963":[{"id":"SV4a-046","name":"Finizen","dexNumber":963,"setId":"SV4a","setName":"Harta Berkilau ex","localId":"046","rarity":"Unknown","imageBase":"","language":"id"},{"id":"SV4a-228","name":"Finizen","dexNumber":963,"setId":"SV4a","setName":"Harta Berkilau ex","localId":"228","rarity":"Unknown","imageBase":"","language":"id"},{"id":"SV8a-044","name":"Finizen","dexNumber":963,"setId":"SV8a","setName":"Festival Terastal ex","localId":"044","rarity":"None","imageBase":"https://assets.tcgdex.net/id/SV/SV8a/044","language":"id","hostedThumbUrl":"https://raw.githubusercontent.com/froyonator/pcc-assets-a/main/id/SV8a/SV8a-044/thumb.webp","hostedFullUrl":"https://raw.githubusercontent.com/froyonator/pcc-assets-a/main/id/SV8a/SV8a-044/original.webp"}],"964":[{"id":"SV4a-047","name":"Palafin","dexNumber":964,"setId":"SV4a","setName":"Harta Berkilau ex","localId":"047","rarity":"Unknown","imageBase":"","language":"id"},{"id":"SV4a-229","name":"Palafin","dexNumber":964,"setId":"SV4a","setName":"Harta Berkilau ex","localId":"229","rarity":"Unknown","imageBase":"","language":"id"},{"id":"SV4a-339","name":"Palafin","dexNumber":964,"setId":"SV4a","setName":"Harta Berkilau ex","localId":"339","rarity":"Unknown","imageBase":"","language":"id"},{"id":"SV8a-045","name":"Palafin","dexNumber":964,"setId":"SV8a","setName":"Festival Terastal ex","localId":"045","rarity":"None","imageBase":"https://assets.tcgdex.net/id/SV/SV8a/045","language":"id","hostedThumbUrl":"https://raw.githubusercontent.com/froyonator/pcc-assets-a/main/id/SV8a/SV8a-045/thumb.webp","hostedFullUrl":"https://raw.githubusercontent.com/froyonator/pcc-assets-a/main/id/SV8a/SV8a-045/original.webp"}],"965":[{"id":"SV1S-059","name":"Varoom","dexNumber":965,"setId":"SV1S","setName":"Scarlet ex","localId":"059","rarity":"Common","imageBase":"","language":"id"},{"id":"SV1S-060","name":"Varoom","dexNumber":965,"setId":"SV1S","setName":"Scarlet ex","localId":"060","rarity":"Common","imageBase":"","language":"id"},{"id":"SV4a-300","name":"Varoom","dexNumber":965,"setId":"SV4a","setName":"Harta Berkilau ex","localId":"300","rarity":"Unknown","imageBase":"","language":"id"},{"id":"SV8a-114","name":"Varoom","dexNumber":965,"setId":"SV8a","setName":"Festival Terastal ex","localId":"114","rarity":"None","imageBase":"https://assets.tcgdex.net/id/SV/SV8a/114","language":"id","hostedThumbUrl":"https://raw.githubusercontent.com/froyonator/pcc-assets-a/main/id/SV8a/SV8a-114/thumb.webp","hostedFullUrl":"https://raw.githubusercontent.com/froyonator/pcc-assets-a/main/id/SV8a/SV8a-114/original.webp"}],"966":[{"id":"SV1S-061","name":"Revavroom","dexNumber":966,"setId":"SV1S","setName":"Scarlet ex","localId":"061","rarity":"Rare","imageBase":"","language":"id"},{"id":"SV4a-301","name":"Revavroom","dexNumber":966,"setId":"SV4a","setName":"Harta Berkilau ex","localId":"301","rarity":"Unknown","imageBase":"","language":"id"},{"id":"SV8a-115","name":"Revavroom","dexNumber":966,"setId":"SV8a","setName":"Festival Terastal ex","localId":"115","rarity":"None","imageBase":"https://assets.tcgdex.net/id/SV/SV8a/115","language":"id","hostedThumbUrl":"https://raw.githubusercontent.com/froyonator/pcc-assets-a/main/id/SV8a/SV8a-115/thumb.webp","hostedFullUrl":"https://raw.githubusercontent.com/froyonator/pcc-assets-a/main/id/SV8a/SV8a-115/original.webp"}],"967":[{"id":"SV1V-068","name":"Cyclizar","dexNumber":967,"setId":"SV1V","setName":"Violet ex","localId":"068","rarity":"Rare","imageBase":"","language":"id"},{"id":"SV4a-303","name":"Cyclizar","dexNumber":967,"setId":"SV4a","setName":"Harta Berkilau ex","localId":"303","rarity":"Unknown","imageBase":"","language":"id"}],"968":[{"id":"SV2P-055","name":"Orthworm","dexNumber":968,"setId":"SV2P","setName":"Mara Bahaya Salju","localId":"055","rarity":"Rare","imageBase":"","language":"id"}],"969":[{"id":"SV2P-042","name":"Glimmet","dexNumber":969,"setId":"SV2P","setName":"Mara Bahaya Salju","localId":"042","rarity":"Common","imageBase":"","language":"id"},{"id":"SV2P-043","name":"Glimmet","dexNumber":969,"setId":"SV2P","setName":"Mara Bahaya Salju","localId":"043","rarity":"Common","imageBase":"","language":"id"},{"id":"SV4a-110","name":"Glimmet","dexNumber":969,"setId":"SV4a","setName":"Harta Berkilau ex","localId":"110","rarity":"Unknown","imageBase":"","language":"id"},{"id":"SV4a-286","name":"Glimmet","dexNumber":969,"setId":"SV4a","setName":"Harta Berkilau ex","localId":"286","rarity":"Unknown","imageBase":"","language":"id"}],"970":[{"id":"SV2P-044","name":"Glimmora","dexNumber":970,"setId":"SV2P","setName":"Mara Bahaya Salju","localId":"044","rarity":"Rare","imageBase":"","language":"id"}],"971":[{"id":"SV1V-046","name":"Greavard","dexNumber":971,"setId":"SV1V","setName":"Violet ex","localId":"046","rarity":"Common","imageBase":"","language":"id"},{"id":"SV1V-047","name":"Greavard","dexNumber":971,"setId":"SV1V","setName":"Violet ex","localId":"047","rarity":"Common","imageBase":"","language":"id"},{"id":"SV4a-097","name":"Greavard","dexNumber":971,"setId":"SV4a","setName":"Harta Berkilau ex","localId":"097","rarity":"Unknown","imageBase":"","language":"id"},{"id":"SV4a-274","name":"Greavard","dexNumber":971,"setId":"SV4a","setName":"Harta Berkilau ex","localId":"274","rarity":"Unknown","imageBase":"","language":"id"}],"972":[{"id":"SV1V-048","name":"Houndstone","dexNumber":972,"setId":"SV1V","setName":"Violet ex","localId":"048","rarity":"Rare","imageBase":"","language":"id"},{"id":"SV4a-098","name":"Houndstone","dexNumber":972,"setId":"SV4a","setName":"Harta Berkilau ex","localId":"098","rarity":"Unknown","imageBase":"","language":"id"},{"id":"SV4a-275","name":"Houndstone","dexNumber":972,"setId":"SV4a","setName":"Harta Berkilau ex","localId":"275","rarity":"Unknown","imageBase":"","language":"id"}],"973":[{"id":"SV2D-065","name":"Flamigo","dexNumber":973,"setId":"SV2D","setName":"Letusan Tanah","localId":"065","rarity":"Uncommon","imageBase":"","language":"id"},{"id":"SV4a-319","name":"Flamigo","dexNumber":973,"setId":"SV4a","setName":"Harta Berkilau ex","localId":"319","rarity":"Unknown","imageBase":"","language":"id"}],"974":[{"id":"SV1V-023","name":"Cetoddle","dexNumber":974,"setId":"SV1V","setName":"Violet ex","localId":"023","rarity":"Common","imageBase":"","language":"id"},{"id":"SV1V-024","name":"Cetoddle","dexNumber":974,"setId":"SV1V","setName":"Violet ex","localId":"024","rarity":"Common","imageBase":"","language":"id"},{"id":"SV2P-020","name":"Cetoddle","dexNumber":974,"setId":"SV2P","setName":"Mara Bahaya Salju","localId":"020","rarity":"Common","imageBase":"https://assets.tcgdex.net/id/SV/SV2P/020","language":"id","hostedThumbUrl":"https://raw.githubusercontent.com/froyonator/pcc-assets-a/main/id/SV2P/SV2P-020/thumb.webp","hostedFullUrl":"https://raw.githubusercontent.com/froyonator/pcc-assets-a/main/id/SV2P/SV2P-020/original.webp"},{"id":"SV2P-021","name":"Cetoddle","dexNumber":974,"setId":"SV2P","setName":"Mara Bahaya Salju","localId":"021","rarity":"Common","imageBase":"","language":"id"}],"975":[{"id":"SV1V-025","name":"Cetitan","dexNumber":975,"setId":"SV1V","setName":"Violet ex","localId":"025","rarity":"Uncommon","imageBase":"","language":"id"},{"id":"SV2P-022","name":"Cetitan","dexNumber":975,"setId":"SV2P","setName":"Mara Bahaya Salju","localId":"022","rarity":"Uncommon","imageBase":"","language":"id"}],"976":[{"id":"SV2P-023","name":"Veluza","dexNumber":976,"setId":"SV2P","setName":"Mara Bahaya Salju","localId":"023","rarity":"Rare","imageBase":"","language":"id"},{"id":"SV4a-048","name":"Veluza","dexNumber":976,"setId":"SV4a","setName":"Harta Berkilau ex","localId":"048","rarity":"Unknown","imageBase":"","language":"id"},{"id":"SV4a-230","name":"Veluza","dexNumber":976,"setId":"SV4a","setName":"Harta Berkilau ex","localId":"230","rarity":"Unknown","imageBase":"","language":"id"}],"977":[{"id":"SV1S-021","name":"Dondozo","dexNumber":977,"setId":"SV1S","setName":"Scarlet ex","localId":"021","rarity":"Rare","imageBase":"","language":"id"},{"id":"SV4a-049","name":"Dondozo","dexNumber":977,"setId":"SV4a","setName":"Harta Berkilau ex","localId":"049","rarity":"Unknown","imageBase":"","language":"id"},{"id":"SV4a-231","name":"Dondozo","dexNumber":977,"setId":"SV4a","setName":"Harta Berkilau ex","localId":"231","rarity":"Unknown","imageBase":"","language":"id"}],"978":[{"id":"SV1S-022","name":"Tatsugiri","dexNumber":978,"setId":"SV1S","setName":"Scarlet ex","localId":"022","rarity":"Uncommon","imageBase":"","language":"id"},{"id":"SV4a-050","name":"Tatsugiri","dexNumber":978,"setId":"SV4a","setName":"Harta Berkilau ex","localId":"050","rarity":"Unknown","imageBase":"","language":"id"},{"id":"SV4a-232","name":"Tatsugiri","dexNumber":978,"setId":"SV4a","setName":"Harta Berkilau ex","localId":"232","rarity":"Unknown","imageBase":"","language":"id"},{"id":"SV8a-121","name":"Tatsugiri","dexNumber":978,"setId":"SV8a","setName":"Festival Terastal ex","localId":"121","rarity":"None","imageBase":"https://assets.tcgdex.net/id/SV/SV8a/121","language":"id","hostedThumbUrl":"https://raw.githubusercontent.com/froyonator/pcc-assets-a/main/id/SV8a/SV8a-121/thumb.webp","hostedFullUrl":"https://raw.githubusercontent.com/froyonator/pcc-assets-a/main/id/SV8a/SV8a-121/original.webp"}],"979":[{"id":"SV1V-051","name":"Annihilape","dexNumber":979,"setId":"SV1V","setName":"Violet ex","localId":"051","rarity":"Rare","imageBase":"","language":"id"},{"id":"SV4a-102","name":"Annihilape","dexNumber":979,"setId":"SV4a","setName":"Harta Berkilau ex","localId":"102","rarity":"Unknown","imageBase":"","language":"id"},{"id":"SV4a-278","name":"Annihilape","dexNumber":979,"setId":"SV4a","setName":"Harta Berkilau ex","localId":"278","rarity":"Unknown","imageBase":"","language":"id"}],"981":[{"id":"SV2D-060","name":"Farigiraf","dexNumber":981,"setId":"SV2D","setName":"Letusan Tanah","localId":"060","rarity":"Uncommon","imageBase":"","language":"id"}],"982":[{"id":"SV2P-057","name":"Dudunsparce","dexNumber":982,"setId":"SV2P","setName":"Mara Bahaya Salju","localId":"057","rarity":"Uncommon","imageBase":"","language":"id"},{"id":"SV8a-130","name":"Dudunsparce","dexNumber":982,"setId":"SV8a","setName":"Festival Terastal ex","localId":"130","rarity":"None","imageBase":"https://assets.tcgdex.net/id/SV/SV8a/130","language":"id","hostedThumbUrl":"https://raw.githubusercontent.com/froyonator/pcc-assets-a/main/id/SV8a/SV8a-130/thumb.webp","hostedFullUrl":"https://raw.githubusercontent.com/froyonator/pcc-assets-a/main/id/SV8a/SV8a-130/original.webp"}],"983":[{"id":"SV1S-058","name":"Kingambit","dexNumber":983,"setId":"SV1S","setName":"Scarlet ex","localId":"058","rarity":"Rare","imageBase":"","language":"id"},{"id":"SV4a-124","name":"Kingambit","dexNumber":983,"setId":"SV4a","setName":"Harta Berkilau ex","localId":"124","rarity":"Unknown","imageBase":"","language":"id"},{"id":"SV4a-294","name":"Kingambit","dexNumber":983,"setId":"SV4a","setName":"Harta Berkilau ex","localId":"294","rarity":"Unknown","imageBase":"","language":"id"}],"984":[{"id":"SV8a-086","name":"Great Tusk","dexNumber":984,"setId":"SV8a","setName":"Festival Terastal ex","localId":"086","rarity":"None","imageBase":"https://assets.tcgdex.net/id/SV/SV8a/086","language":"id","hostedThumbUrl":"https://raw.githubusercontent.com/froyonator/pcc-assets-a/main/id/SV8a/SV8a-086/thumb.webp","hostedFullUrl":"https://raw.githubusercontent.com/froyonator/pcc-assets-a/main/id/SV8a/SV8a-086/original.webp"}],"985":[{"id":"SV8a-071","name":"Scream Tail","dexNumber":985,"setId":"SV8a","setName":"Festival Terastal ex","localId":"071","rarity":"None","imageBase":"https://assets.tcgdex.net/id/SV/SV8a/071","language":"id","hostedThumbUrl":"https://raw.githubusercontent.com/froyonator/pcc-assets-a/main/id/SV8a/SV8a-071/thumb.webp","hostedFullUrl":"https://raw.githubusercontent.com/froyonator/pcc-assets-a/main/id/SV8a/SV8a-071/original.webp"}],"986":[{"id":"SV8a-099","name":"Brute Bonnet","dexNumber":986,"setId":"SV8a","setName":"Festival Terastal ex","localId":"099","rarity":"None","imageBase":"https://assets.tcgdex.net/id/SV/SV8a/099","language":"id","hostedThumbUrl":"https://raw.githubusercontent.com/froyonator/pcc-assets-a/main/id/SV8a/SV8a-099/thumb.webp","hostedFullUrl":"https://raw.githubusercontent.com/froyonator/pcc-assets-a/main/id/SV8a/SV8a-099/original.webp"}],"987":[{"id":"SV8a-072","name":"Flutter Mane","dexNumber":987,"setId":"SV8a","setName":"Festival Terastal ex","localId":"072","rarity":"None","imageBase":"https://assets.tcgdex.net/id/SV/SV8a/072","language":"id","hostedThumbUrl":"https://raw.githubusercontent.com/froyonator/pcc-assets-a/main/id/SV8a/SV8a-072/thumb.webp","hostedFullUrl":"https://raw.githubusercontent.com/froyonator/pcc-assets-a/main/id/SV8a/SV8a-072/original.webp"}],"988":[{"id":"SV8a-087","name":"Slither Wing","dexNumber":988,"setId":"SV8a","setName":"Festival Terastal ex","localId":"087","rarity":"None","imageBase":"https://assets.tcgdex.net/id/SV/SV8a/087","language":"id","hostedThumbUrl":"https://raw.githubusercontent.com/froyonator/pcc-assets-a/main/id/SV8a/SV8a-087/thumb.webp","hostedFullUrl":"https://raw.githubusercontent.com/froyonator/pcc-assets-a/main/id/SV8a/SV8a-087/original.webp"}],"990":[{"id":"SV8a-116","name":"Iron Treads","dexNumber":990,"setId":"SV8a","setName":"Festival Terastal ex","localId":"116","rarity":"None","imageBase":"https://assets.tcgdex.net/id/SV/SV8a/116","language":"id","hostedThumbUrl":"https://raw.githubusercontent.com/froyonator/pcc-assets-a/main/id/SV8a/SV8a-116/thumb.webp","hostedFullUrl":"https://raw.githubusercontent.com/froyonator/pcc-assets-a/main/id/SV8a/SV8a-116/original.webp"}],"991":[{"id":"SV8a-047","name":"Iron Bundle","dexNumber":991,"setId":"SV8a","setName":"Festival Terastal ex","localId":"047","rarity":"None","imageBase":"https://assets.tcgdex.net/id/SV/SV8a/047","language":"id","hostedThumbUrl":"https://raw.githubusercontent.com/froyonator/pcc-assets-a/main/id/SV8a/SV8a-047/thumb.webp","hostedFullUrl":"https://raw.githubusercontent.com/froyonator/pcc-assets-a/main/id/SV8a/SV8a-047/original.webp"}],"993":[{"id":"SV8a-135","name":"Iron Jugulis","dexNumber":993,"setId":"SV8a","setName":"Festival Terastal ex","localId":"135","rarity":"None","imageBase":"https://assets.tcgdex.net/id/SV/SV8a/135","language":"id","hostedThumbUrl":"https://raw.githubusercontent.com/froyonator/pcc-assets-a/main/id/SV8a/SV8a-135/thumb.webp","hostedFullUrl":"https://raw.githubusercontent.com/froyonator/pcc-assets-a/main/id/SV8a/SV8a-135/original.webp"}],"994":[{"id":"SV8a-024","name":"Iron Moth","dexNumber":994,"setId":"SV8a","setName":"Festival Terastal ex","localId":"024","rarity":"None","imageBase":"https://assets.tcgdex.net/id/SV/SV8a/024","language":"id","hostedThumbUrl":"https://raw.githubusercontent.com/froyonator/pcc-assets-a/main/id/SV8a/SV8a-024/thumb.webp","hostedFullUrl":"https://raw.githubusercontent.com/froyonator/pcc-assets-a/main/id/SV8a/SV8a-024/original.webp"}],"995":[{"id":"SV8a-055","name":"Iron Thorns","dexNumber":995,"setId":"SV8a","setName":"Festival Terastal ex","localId":"055","rarity":"None","imageBase":"https://assets.tcgdex.net/id/SV/SV8a/055","language":"id","hostedThumbUrl":"https://raw.githubusercontent.com/froyonator/pcc-assets-a/main/id/SV8a/SV8a-055/thumb.webp","hostedFullUrl":"https://raw.githubusercontent.com/froyonator/pcc-assets-a/main/id/SV8a/SV8a-055/original.webp"}],"996":[{"id":"SV2P-024","name":"Frigibax","dexNumber":996,"setId":"SV2P","setName":"Mara Bahaya Salju","localId":"024","rarity":"Common","imageBase":"","language":"id"},{"id":"SV2P-025","name":"Frigibax","dexNumber":996,"setId":"SV2P","setName":"Mara Bahaya Salju","localId":"025","rarity":"Common","imageBase":"","language":"id"},{"id":"SV4a-051","name":"Frigibax","dexNumber":996,"setId":"SV4a","setName":"Harta Berkilau ex","localId":"051","rarity":"Unknown","imageBase":"","language":"id"},{"id":"SV4a-233","name":"Frigibax","dexNumber":996,"setId":"SV4a","setName":"Harta Berkilau ex","localId":"233","rarity":"Unknown","imageBase":"","language":"id"}],"997":[{"id":"SV2P-026","name":"Arctibax","dexNumber":997,"setId":"SV2P","setName":"Mara Bahaya Salju","localId":"026","rarity":"Common","imageBase":"","language":"id"},{"id":"SV4a-052","name":"Arctibax","dexNumber":997,"setId":"SV4a","setName":"Harta Berkilau ex","localId":"052","rarity":"Unknown","imageBase":"","language":"id"},{"id":"SV4a-234","name":"Arctibax","dexNumber":997,"setId":"SV4a","setName":"Harta Berkilau ex","localId":"234","rarity":"Unknown","imageBase":"","language":"id"}],"998":[{"id":"SV2P-027","name":"Baxcalibur","dexNumber":998,"setId":"SV2P","setName":"Mara Bahaya Salju","localId":"027","rarity":"Rare","imageBase":"","language":"id"},{"id":"SV4a-053","name":"Baxcalibur","dexNumber":998,"setId":"SV4a","setName":"Harta Berkilau ex","localId":"053","rarity":"Unknown","imageBase":"","language":"id"},{"id":"SV4a-235","name":"Baxcalibur","dexNumber":998,"setId":"SV4a","setName":"Harta Berkilau ex","localId":"235","rarity":"Unknown","imageBase":"","language":"id"}],"999":[{"id":"SV4a-099","name":"Gimmighoul","dexNumber":999,"setId":"SV4a","setName":"Harta Berkilau ex","localId":"099","rarity":"Unknown","imageBase":"","language":"id"},{"id":"SV8a-073","name":"Gimmighoul","dexNumber":999,"setId":"SV8a","setName":"Festival Terastal ex","localId":"073","rarity":"None","imageBase":"https://assets.tcgdex.net/id/SV/SV8a/073","language":"id","hostedThumbUrl":"https://raw.githubusercontent.com/froyonator/pcc-assets-a/main/id/SV8a/SV8a-073/thumb.webp","hostedFullUrl":"https://raw.githubusercontent.com/froyonator/pcc-assets-a/main/id/SV8a/SV8a-073/original.webp"}],"1001":[{"id":"SV8a-015","name":"Wo-Chien","dexNumber":1001,"setId":"SV8a","setName":"Festival Terastal ex","localId":"015","rarity":"None","imageBase":"https://assets.tcgdex.net/id/SV/SV8a/015","language":"id","hostedThumbUrl":"https://raw.githubusercontent.com/froyonator/pcc-assets-a/main/id/SV8a/SV8a-015/thumb.webp","hostedFullUrl":"https://raw.githubusercontent.com/froyonator/pcc-assets-a/main/id/SV8a/SV8a-015/original.webp"}],"1002":[{"id":"SV8a-048","name":"Chien-Pao","dexNumber":1002,"setId":"SV8a","setName":"Festival Terastal ex","localId":"048","rarity":"None","imageBase":"https://assets.tcgdex.net/id/SV/SV8a/048","language":"id","hostedThumbUrl":"https://raw.githubusercontent.com/froyonator/pcc-assets-a/main/id/SV8a/SV8a-048/thumb.webp","hostedFullUrl":"https://raw.githubusercontent.com/froyonator/pcc-assets-a/main/id/SV8a/SV8a-048/original.webp"}],"1003":[{"id":"SV8a-089","name":"Ting-Lu","dexNumber":1003,"setId":"SV8a","setName":"Festival Terastal ex","localId":"089","rarity":"None","imageBase":"https://assets.tcgdex.net/id/SV/SV8a/089","language":"id","hostedThumbUrl":"https://raw.githubusercontent.com/froyonator/pcc-assets-a/main/id/SV8a/SV8a-089/thumb.webp","hostedFullUrl":"https://raw.githubusercontent.com/froyonator/pcc-assets-a/main/id/SV8a/SV8a-089/original.webp"}],"1004":[{"id":"SV8a-025","name":"Chi-Yu","dexNumber":1004,"setId":"SV8a","setName":"Festival Terastal ex","localId":"025","rarity":"None","imageBase":"https://assets.tcgdex.net/id/SV/SV8a/025","language":"id","hostedThumbUrl":"https://raw.githubusercontent.com/froyonator/pcc-assets-a/main/id/SV8a/SV8a-025/thumb.webp","hostedFullUrl":"https://raw.githubusercontent.com/froyonator/pcc-assets-a/main/id/SV8a/SV8a-025/original.webp"}],"1005":[{"id":"SV8a-100","name":"Roaring Moon","dexNumber":1005,"setId":"SV8a","setName":"Festival Terastal ex","localId":"100","rarity":"None","imageBase":"https://assets.tcgdex.net/id/SV/SV8a/100","language":"id","hostedThumbUrl":"https://raw.githubusercontent.com/froyonator/pcc-assets-a/main/id/SV8a/SV8a-100/thumb.webp","hostedFullUrl":"https://raw.githubusercontent.com/froyonator/pcc-assets-a/main/id/SV8a/SV8a-100/original.webp"}],"1007":[{"id":"SV8a-122","name":"Koraidon","dexNumber":1007,"setId":"SV8a","setName":"Festival Terastal ex","localId":"122","rarity":"None","imageBase":"https://assets.tcgdex.net/id/SV/SV8a/122","language":"id","hostedThumbUrl":"https://raw.githubusercontent.com/froyonator/pcc-assets-a/main/id/SV8a/SV8a-122/thumb.webp","hostedFullUrl":"https://raw.githubusercontent.com/froyonator/pcc-assets-a/main/id/SV8a/SV8a-122/original.webp"}],"1008":[{"id":"SV8a-123","name":"Miraidon","dexNumber":1008,"setId":"SV8a","setName":"Festival Terastal ex","localId":"123","rarity":"None","imageBase":"https://assets.tcgdex.net/id/SV/SV8a/123","language":"id","hostedThumbUrl":"https://raw.githubusercontent.com/froyonator/pcc-assets-a/main/id/SV8a/SV8a-123/thumb.webp","hostedFullUrl":"https://raw.githubusercontent.com/froyonator/pcc-assets-a/main/id/SV8a/SV8a-123/original.webp"}],"1011":[{"id":"SV8a-009","name":"Dipplin","dexNumber":1011,"setId":"SV8a","setName":"Festival Terastal ex","localId":"009","rarity":"None","imageBase":"https://assets.tcgdex.net/id/SV/SV8a/009","language":"id","hostedThumbUrl":"https://raw.githubusercontent.com/froyonator/pcc-assets-a/main/id/SV8a/SV8a-009/thumb.webp","hostedFullUrl":"https://raw.githubusercontent.com/froyonator/pcc-assets-a/main/id/SV8a/SV8a-009/original.webp"}],"1012":[{"id":"SV8a-017","name":"Poltchageist","dexNumber":1012,"setId":"SV8a","setName":"Festival Terastal ex","localId":"017","rarity":"None","imageBase":"https://assets.tcgdex.net/id/SV/SV8a/017","language":"id","hostedThumbUrl":"https://raw.githubusercontent.com/froyonator/pcc-assets-a/main/id/SV8a/SV8a-017/thumb.webp","hostedFullUrl":"https://raw.githubusercontent.com/froyonator/pcc-assets-a/main/id/SV8a/SV8a-017/original.webp"}],"1013":[{"id":"SV8a-018","name":"Sinistcha","dexNumber":1013,"setId":"SV8a","setName":"Festival Terastal ex","localId":"018","rarity":"None","imageBase":"https://assets.tcgdex.net/id/SV/SV8a/018","language":"id","hostedThumbUrl":"https://raw.githubusercontent.com/froyonator/pcc-assets-a/main/id/SV8a/SV8a-018/thumb.webp","hostedFullUrl":"https://raw.githubusercontent.com/froyonator/pcc-assets-a/main/id/SV8a/SV8a-018/original.webp"}],"1014":[{"id":"SV8a-090","name":"Okidogi","dexNumber":1014,"setId":"SV8a","setName":"Festival Terastal ex","localId":"090","rarity":"None","imageBase":"https://assets.tcgdex.net/id/SV/SV8a/090","language":"id","hostedThumbUrl":"https://raw.githubusercontent.com/froyonator/pcc-assets-a/main/id/SV8a/SV8a-090/thumb.webp","hostedFullUrl":"https://raw.githubusercontent.com/froyonator/pcc-assets-a/main/id/SV8a/SV8a-090/original.webp"}],"1015":[{"id":"SV8a-075","name":"Munkidori","dexNumber":1015,"setId":"SV8a","setName":"Festival Terastal ex","localId":"075","rarity":"None","imageBase":"https://assets.tcgdex.net/id/SV/SV8a/075","language":"id","hostedThumbUrl":"https://raw.githubusercontent.com/froyonator/pcc-assets-a/main/id/SV8a/SV8a-075/thumb.webp","hostedFullUrl":"https://raw.githubusercontent.com/froyonator/pcc-assets-a/main/id/SV8a/SV8a-075/original.webp"}],"1016":[{"id":"SV8a-076","name":"Fezandipiti","dexNumber":1016,"setId":"SV8a","setName":"Festival Terastal ex","localId":"076","rarity":"None","imageBase":"https://assets.tcgdex.net/id/SV/SV8a/076","language":"id","hostedThumbUrl":"https://raw.githubusercontent.com/froyonator/pcc-assets-a/main/id/SV8a/SV8a-076/thumb.webp","hostedFullUrl":"https://raw.githubusercontent.com/froyonator/pcc-assets-a/main/id/SV8a/SV8a-076/original.webp"}],"1018":[{"id":"SV8a-113","name":"Archaludon","dexNumber":1018,"setId":"SV8a","setName":"Festival Terastal ex","localId":"113","rarity":"None","imageBase":"https://assets.tcgdex.net/id/SV/SV8a/113","language":"id","hostedThumbUrl":"https://raw.githubusercontent.com/froyonator/pcc-assets-a/main/id/SV8a/SV8a-113/thumb.webp","hostedFullUrl":"https://raw.githubusercontent.com/froyonator/pcc-assets-a/main/id/SV8a/SV8a-113/original.webp"}],"1022":[{"id":"SV8a-077","name":"Iron Boulder","dexNumber":1022,"setId":"SV8a","setName":"Festival Terastal ex","localId":"077","rarity":"None","imageBase":"https://assets.tcgdex.net/id/SV/SV8a/077","language":"id","hostedThumbUrl":"https://raw.githubusercontent.com/froyonator/pcc-assets-a/main/id/SV8a/SV8a-077/thumb.webp","hostedFullUrl":"https://raw.githubusercontent.com/froyonator/pcc-assets-a/main/id/SV8a/SV8a-077/original.webp"}]}